{
  "parameters": {
    "iterations": 100,
    "population_size": 250,
    "max_generations": 2000,
    "crossover_rate": 0.8,
    "mutation_rate": 0.35,
    "tournament_size": 2,
    "elitism_ratio": 0.04,
    "head_length": 3,
    "delay": 1
  },
  "results": [
    {
      "iteration": 1,
      "generations": 30,
      "best_fitness": 1.0,
      "perfect_found": true,
      "final_avg_fitness": 0.21489802477450576,
      "best_individual": {
        "expression": {
          "Individual": {
            "Head": "['@2', 'x0', '@1']",
            "Tail": "['@2', '@1', '@2', '@1']",
            "Weights": "[-0.9346461962352581, -0.005098746755960809, 1.0963301255798499, -1.8537951350355777, 1.1111528979339234, -1.3010424530641742]",
            "Biases": "[-0.032454360158836404, -1.1073221069683081, 1.2698335449509977]"
          }
        },
        "fitness": 1.0
      }
    },
    {
      "iteration": 2,
      "generations": 4,
      "best_fitness": 1.0,
      "perfect_found": true,
      "final_avg_fitness": 0.1161158395409584,
      "best_individual": {
        "expression": {
          "Individual": {
            "Head": "['@2', 'x0', '@1']",
            "Tail": "['@0', 'x0', '@1', '@1']",
            "Weights": "[-0.2996782343036526, 1.238613068355527, -0.3620830430210514, 2.152537589558571, -0.4605558679976278, -0.9837667884209964]",
            "Biases": "[0.17916039748525137, -0.05683736619760305, -1.686147593265279]"
          }
        },
        "fitness": 1.0
      }
    },
    {
      "iteration": 3,
      "generations": 13,
      "best_fitness": 1.0,
      "perfect_found": true,
      "final_avg_fitness": 0.19594177026301624,
      "best_individual": {
        "expression": {
          "Individual": {
            "Head": "['@2', 'x0', '@1']",
            "Tail": "['@0', 'x0', '@0', '@1']",
            "Weights": "[0.3430201219868472, 1.5472861627878567, -0.6259389186155333, -0.38361237877224874, 0.37442693225150253, 0.19064718710365502]",
            "Biases": "[0.19849552311978633, -0.8350934949016539, -1.6850516178445818]"
          }
        },
        "fitness": 1.0
      }
    },
    {
      "iteration": 4,
      "generations": 143,
      "best_fitness": 0.9999990186062178,
      "perfect_found": true,
      "final_avg_fitness": 0.17767456088110567,
      "best_individual": {
        "expression": {
          "Individual": {
            "Head": "['add', 'add', 'x0']",
            "Tail": "['@2', 'x0', '@1', '@2']",
            "Weights": "[0.5087203308739249, -0.5526227421826834, 1.9660023039576662, 1.0881304046598008, 0.9040261287621301, -0.2457839448981902]",
            "Biases": "[-0.023763706996163713, 0.04326887107482068, 1.7658846710990064]"
          }
        },
        "fitness": 0.9999990186062178
      }
    },
    {
      "iteration": 5,
      "generations": 530,
      "best_fitness": 1.0,
      "perfect_found": true,
      "final_avg_fitness": 0.23032641907402648,
      "best_individual": {
        "expression": {
          "Individual": {
            "Head": "['@2', 'x0', '@1']",
            "Tail": "['@2', '@0', '@1', '@1']",
            "Weights": "[0.8521829065689126, 0.0014655325799777519, 1.6223779859142047, -0.04579913944776598, 0.8335278236980155, -1.8273136244129922]",
            "Biases": "[0.10906567398567996, -0.1440040491842038, -0.817943097714648]"
          }
        },
        "fitness": 1.0
      }
    },
    {
      "iteration": 6,
      "generations": 109,
      "best_fitness": 1.0,
      "perfect_found": true,
      "final_avg_fitness": 0.21824764436155603,
      "best_individual": {
        "expression": {
          "Individual": {
            "Head": "['@2', 'x0', '@1']",
            "Tail": "['@2', 'x0', '@1', '@1']",
            "Weights": "[0.6669424428666153, -0.02230734680738212, -1.5627232046199313, -0.30419735601065434, -1.1325423213591208, -1.1248259924024078]",
            "Biases": "[-0.3502072263460057, 2.618976426488796, -1.9547059828592581]"
          }
        },
        "fitness": 1.0
      }
    },
    {
      "iteration": 7,
      "generations": 4,
      "best_fitness": 1.0,
      "perfect_found": true,
      "final_avg_fitness": 0.08666219900548458,
      "best_individual": {
        "expression": {
          "Individual": {
            "Head": "['@2', 'x0', '@1']",
            "Tail": "['x0', '@1', '@1', 'x0']",
            "Weights": "[-0.31496462621474364, 0.7732193055534161, -1.000370767172755, -0.39091600366340795, -0.18722884791389352, 0.2499814659256659]",
            "Biases": "[-1.2949689222012488, 0.521976577804995, 1.1840530052409097]"
          }
        },
        "fitness": 1.0
      }
    },
    {
      "iteration": 8,
      "generations": 4,
      "best_fitness": 1.0,
      "perfect_found": true,
      "final_avg_fitness": 0.1633722501215525,
      "best_individual": {
        "expression": {
          "Individual": {
            "Head": "['@2', 'x0', '@1']",
            "Tail": "['@0', 'x0', 'x0', '@1']",
            "Weights": "[0.02854808166817146, 0.9827091342809835, 2.1385261322764926, -1.5431124731767274, 0.6108856367566732, -0.1434821260140316]",
            "Biases": "[-0.096512001021314, 1.4597417342860168, 0.18881652355178424]"
          }
        },
        "fitness": 1.0
      }
    },
    {
      "iteration": 9,
      "generations": 6,
      "best_fitness": 1.0,
      "perfect_found": true,
      "final_avg_fitness": 0.20317619160562753,
      "best_individual": {
        "expression": {
          "Individual": {
            "Head": "['@2', 'x0', '@1']",
            "Tail": "['@1', '@1', 'x0', '@2']",
            "Weights": "[-0.23909060278460262, 0.9107831663753212, 0.09473791438573692, -0.3712914391409578, -0.4913271174022442, 0.07859044834207216]",
            "Biases": "[1.3503904356064855, -0.06164481049202211, -1.2316972898889902]"
          }
        },
        "fitness": 1.0
      }
    },
    {
      "iteration": 10,
      "generations": 13,
      "best_fitness": 1.0,
      "perfect_found": true,
      "final_avg_fitness": 0.1598514561355114,
      "best_individual": {
        "expression": {
          "Individual": {
            "Head": "['@2', 'x0', '@1']",
            "Tail": "['@1', '@2', '@0', '@0']",
            "Weights": "[-0.0018479136056633572, -2.4588063792851544, -0.17543104965250322, 0.40766196112555086, 0.41182067410985007, 0.7426403729922181]",
            "Biases": "[-0.172728560146727, -0.8993682244456966, 1.3782060882019274]"
          }
        },
        "fitness": 1.0
      }
    },
    {
      "iteration": 11,
      "generations": 11,
      "best_fitness": 1.0,
      "perfect_found": true,
      "final_avg_fitness": 0.10708541175723076,
      "best_individual": {
        "expression": {
          "Individual": {
            "Head": "['@2', 'x0', '@1']",
            "Tail": "['@2', '@2', '@0', 'x0']",
            "Weights": "[-0.031702734798735394, -1.000939159349497, 0.7188165277875058, 0.6868050151473493, 1.1589328530097591, -2.8119748559880895]",
            "Biases": "[0.27540907932192166, -0.45603704937491024, 1.2462084682220227]"
          }
        },
        "fitness": 1.0
      }
    },
    {
      "iteration": 12,
      "generations": 1,
      "best_fitness": 1.0,
      "perfect_found": true,
      "final_avg_fitness": 0.02726114559173584,
      "best_individual": {
        "expression": {
          "Individual": {
            "Head": "['@2', 'x0', '@1']",
            "Tail": "['@1', '@0', '@1', '@1']",
            "Weights": "[-0.17878944626645157, 0.2425005429096791, 1.2687737478733923, 0.5977766835631617, 0.38429068536762956, -1.966212521673293]",
            "Biases": "[-0.4711494066077483, 0.6402510699865194, 1.062102245369669]"
          }
        },
        "fitness": 1.0
      }
    },
    {
      "iteration": 13,
      "generations": 2,
      "best_fitness": 1.0,
      "perfect_found": true,
      "final_avg_fitness": 0.05520972323417664,
      "best_individual": {
        "expression": {
          "Individual": {
            "Head": "['@2', 'x0', '@1']",
            "Tail": "['@1', '@0', '@1', '@0']",
            "Weights": "[0.8804635165688391, 1.6134531843975022, -0.8019586594148862, 2.1538948643752174, -0.6374778712074524, -0.030234957131431067]",
            "Biases": "[-0.12019411428062958, -0.2944312377700361, -1.1015659383566032]"
          }
        },
        "fitness": 1.0
      }
    },
    {
      "iteration": 14,
      "generations": 3,
      "best_fitness": 1.0,
      "perfect_found": true,
      "final_avg_fitness": 0.048390120625495914,
      "best_individual": {
        "expression": {
          "Individual": {
            "Head": "['@2', 'x0', '@1']",
            "Tail": "['@2', 'x0', '@0', 'x0']",
            "Weights": "[0.1963401195751721, 0.7289622135099093, 0.9247719839611394, 0.2601496571841837, 0.139508322591439, 0.846407358233058]",
            "Biases": "[-0.060168145021829, -0.2044618277446905, -0.7074348041785062]"
          }
        },
        "fitness": 1.0
      }
    },
    {
      "iteration": 15,
      "generations": 11,
      "best_fitness": 1.0,
      "perfect_found": true,
      "final_avg_fitness": 0.13398577535897493,
      "best_individual": {
        "expression": {
          "Individual": {
            "Head": "['@2', 'x0', '@1']",
            "Tail": "['@2', 'x0', 'x0', '@0']",
            "Weights": "[-0.6576851889334527, 0.7077968723546663, -0.5529887665539093, 1.2155747710384892, 0.7572333934025263, -0.7385528464106366]",
            "Biases": "[0.03254396602062004, 0.16463032898915464, -1.5105874725388313]"
          }
        },
        "fitness": 1.0
      }
    },
    {
      "iteration": 16,
      "generations": 8,
      "best_fitness": 1.0,
      "perfect_found": true,
      "final_avg_fitness": 0.16305493828654288,
      "best_individual": {
        "expression": {
          "Individual": {
            "Head": "['@2', 'x0', '@1']",
            "Tail": "['@0', '@1', '@0', '@2']",
            "Weights": "[1.3641025057301528, -1.4719211523593114, 1.5195558358925942, -1.1123988920340873, 0.0806409451226916, 1.0300159448769082]",
            "Biases": "[-1.718402839812191, 0.13835489858256664, -2.462647674360639]"
          }
        },
        "fitness": 1.0
      }
    },
    {
      "iteration": 17,
      "generations": 4,
      "best_fitness": 1.0,
      "perfect_found": true,
      "final_avg_fitness": 0.05210011720657349,
      "best_individual": {
        "expression": {
          "Individual": {
            "Head": "['@2', 'x0', '@1']",
            "Tail": "['@2', '@2', 'x0', 'x0']",
            "Weights": "[1.112588094671003, 0.7665082845347864, 1.8646525179800328, 1.8329979154518048, 0.17484621415564927, -1.0589685932447312]",
            "Biases": "[-0.30341831474542585, -1.3042907272511242, 0.4337730379440572]"
          }
        },
        "fitness": 1.0
      }
    },
    {
      "iteration": 18,
      "generations": 292,
      "best_fitness": 1.0,
      "perfect_found": true,
      "final_avg_fitness": 0.24704044349378454,
      "best_individual": {
        "expression": {
          "Individual": {
            "Head": "['@2', 'x0', '@1']",
            "Tail": "['@2', 'x0', '@2', 'x0']",
            "Weights": "[-0.6418108426242233, 0.013661314110757754, -1.1668811397504275, -0.17529652564173248, 0.43391669879972583, -0.658760565037394]",
            "Biases": "[1.3115648179012789, 1.5390320220879241, 2.3491688493726897]"
          }
        },
        "fitness": 1.0
      }
    },
    {
      "iteration": 19,
      "generations": 8,
      "best_fitness": 1.0,
      "perfect_found": true,
      "final_avg_fitness": 0.2159896011482924,
      "best_individual": {
        "expression": {
          "Individual": {
            "Head": "['@2', 'x0', '@1']",
            "Tail": "['x0', '@2', '@2', 'x0']",
            "Weights": "[-0.41499865254108714, -0.7836944166189145, -0.6424590497418992, -0.41788808801974886, -0.47654056601666783, -0.5997040364257684]",
            "Biases": "[-0.13996902612413598, 1.0289170277342945, -0.362776732032265]"
          }
        },
        "fitness": 1.0
      }
    },
    {
      "iteration": 20,
      "generations": 6,
      "best_fitness": 1.0,
      "perfect_found": true,
      "final_avg_fitness": 0.08019285976886749,
      "best_individual": {
        "expression": {
          "Individual": {
            "Head": "['@2', 'x0', '@1']",
            "Tail": "['@2', '@1', 'x0', '@1']",
            "Weights": "[0.2490252933591588, 1.0537927750739524, 1.4319784593756093, -0.10148586520786726, 2.0926616635430575, 0.6998802862181731]",
            "Biases": "[-0.29938842599714016, 0.23226113317323693, 0.2875675128960846]"
          }
        },
        "fitness": 1.0
      }
    },
    {
      "iteration": 21,
      "generations": 31,
      "best_fitness": 1.0,
      "perfect_found": true,
      "final_avg_fitness": 0.1439437591508031,
      "best_individual": {
        "expression": {
          "Individual": {
            "Head": "['@2', 'x0', '@1']",
            "Tail": "['x0', 'x0', 'x0', 'x0']",
            "Weights": "[-1.6423502927347744, -2.456481868130621, -0.7286434812867784, -0.31669015160686514, 0.9802360495852737, -2.4393810036278207]",
            "Biases": "[0.43461336911580045, -0.18085398199932373, 0.04928865074486362]"
          }
        },
        "fitness": 1.0
      }
    },
    {
      "iteration": 22,
      "generations": 124,
      "best_fitness": 1.0,
      "perfect_found": true,
      "final_avg_fitness": 0.2120059809006625,
      "best_individual": {
        "expression": {
          "Individual": {
            "Head": "['@2', 'x0', '@1']",
            "Tail": "['x0', '@2', 'x0', 'x0']",
            "Weights": "[-0.34797040556181436, 0.35560004280743207, 1.257547293618585, 1.2444714571820823, 5.367196425963422, -5.82155497368313]",
            "Biases": "[-1.5042393821130053, -0.03983338579695678, -1.6341939324120511]"
          }
        },
        "fitness": 1.0
      }
    },
    {
      "iteration": 23,
      "generations": 64,
      "best_fitness": 0.9999998548398139,
      "perfect_found": true,
      "final_avg_fitness": 0.1914960559664039,
      "best_individual": {
        "expression": {
          "Individual": {
            "Head": "['not_f', 'subtract', 'x0']",
            "Tail": "['@2', '@1', '@0', '@0']",
            "Weights": "[-1.1526545669673534, 0.00015725627176929385, -0.8678435960896057, -0.5666702089978662, 0.13738527536434222, -2.4653956787386635]",
            "Biases": "[0.09311395928998162, -0.9479347874229269, -0.5695894551628551]"
          }
        },
        "fitness": 0.9999998548398139
      }
    },
    {
      "iteration": 24,
      "generations": 2,
      "best_fitness": 1.0,
      "perfect_found": true,
      "final_avg_fitness": 0.1058131732493639,
      "best_individual": {
        "expression": {
          "Individual": {
            "Head": "['@2', 'x0', '@1']",
            "Tail": "['@0', 'x0', 'x0', '@0']",
            "Weights": "[-0.19620391465351544, 0.8207761513719618, -0.5521100607834897, 0.4086891694090124, 0.8576657540253565, -0.6239587154831037]",
            "Biases": "[0.6409750645137466, -1.5519911288769028, 0.5036650698735337]"
          }
        },
        "fitness": 1.0
      }
    },
    {
      "iteration": 25,
      "generations": 13,
      "best_fitness": 1.0,
      "perfect_found": true,
      "final_avg_fitness": 0.12660059916973115,
      "best_individual": {
        "expression": {
          "Individual": {
            "Head": "['@2', 'x0', '@1']",
            "Tail": "['@0', '@0', 'x0', '@1']",
            "Weights": "[0.5329379283049869, -1.2966067316923306, -3.0146708760602055, -0.77199861293017, 1.3370321812951615, -1.4803512773019243]",
            "Biases": "[-0.46399135076182174, 1.2249715654725173, -0.630592825741083]"
          }
        },
        "fitness": 1.0
      }
    },
    {
      "iteration": 26,
      "generations": 2,
      "best_fitness": 1.0,
      "perfect_found": true,
      "final_avg_fitness": 0.03857476806640625,
      "best_individual": {
        "expression": {
          "Individual": {
            "Head": "['@2', 'x0', '@1']",
            "Tail": "['x0', '@1', 'x0', '@0']",
            "Weights": "[0.37614665748138976, 2.0780997225787887, 0.5677861476429162, 0.24941650473211915, -0.2606668609436497, 1.204554352671535]",
            "Biases": "[-0.11182190956380864, 1.175845440941827, 0.4172805377839621]"
          }
        },
        "fitness": 1.0
      }
    },
    {
      "iteration": 27,
      "generations": 2,
      "best_fitness": 1.0,
      "perfect_found": true,
      "final_avg_fitness": 0.09477506893873215,
      "best_individual": {
        "expression": {
          "Individual": {
            "Head": "['@2', 'x0', '@1']",
            "Tail": "['@2', '@1', '@0', '@1']",
            "Weights": "[0.32694158640352045, 0.6704801629852913, -1.089970643969349, 1.0448408069067523, 1.166441362241708, -0.3078677436987472]",
            "Biases": "[0.13861607908865947, -0.5614673165883152, 2.4661537003211595]"
          }
        },
        "fitness": 1.0
      }
    },
    {
      "iteration": 28,
      "generations": 4,
      "best_fitness": 1.0,
      "perfect_found": true,
      "final_avg_fitness": 0.20611502619087696,
      "best_individual": {
        "expression": {
          "Individual": {
            "Head": "['@2', 'x0', '@1']",
            "Tail": "['x0', 'x0', 'x0', 'x0']",
            "Weights": "[0.5659131904493775, 1.0444221358363832, 0.8562214700295253, 0.3716549188135986, -0.8984848343963657, -0.24627313963093053]",
            "Biases": "[0.2466004680924428, -0.9328279143069147, 0.778417643029109]"
          }
        },
        "fitness": 1.0
      }
    },
    {
      "iteration": 29,
      "generations": 1,
      "best_fitness": 1.0,
      "perfect_found": true,
      "final_avg_fitness": 0.27151326537132264,
      "best_individual": {
        "expression": {
          "Individual": {
            "Head": "['@2', 'x0', '@1']",
            "Tail": "['@0', '@2', 'x0', '@0']",
            "Weights": "[0.5674292000535329, 0.0680816968604927, 0.09210671514323272, -0.048205283652666624, -1.5951571359020564, -0.46870572769184793]",
            "Biases": "[-1.169002467421697, 0.2857612463593324, -0.9433438959178234]"
          }
        },
        "fitness": 1.0
      }
    },
    {
      "iteration": 30,
      "generations": 2,
      "best_fitness": 1.0,
      "perfect_found": true,
      "final_avg_fitness": 0.15241723208129407,
      "best_individual": {
        "expression": {
          "Individual": {
            "Head": "['@2', 'x0', '@1']",
            "Tail": "['@2', 'x0', '@0', 'x0']",
            "Weights": "[-0.3366435165047108, 1.1134690091280628, 0.05424044872291345, -0.0278512512447133, -0.8884631799908299, -0.28207904401383305]",
            "Biases": "[-0.9828877517599997, -0.2630281485616545, 0.4951825304514362]"
          }
        },
        "fitness": 1.0
      }
    },
    {
      "iteration": 31,
      "generations": 69,
      "best_fitness": 0.9999990989919638,
      "perfect_found": true,
      "final_avg_fitness": 0.23214652515239753,
      "best_individual": {
        "expression": {
          "Individual": {
            "Head": "['add', 'add', 'x0']",
            "Tail": "['x0', '@2', 'x0', 'x0']",
            "Weights": "[-1.725704324594778, -0.1442487682294203, -0.08401800370479459, -0.579450816883744, 0.2947389587856656, 0.47772358307660856]",
            "Biases": "[-0.48020398504066253, -0.2762826858518184, -1.5558726938126046]"
          }
        },
        "fitness": 0.9999990989919638
      }
    },
    {
      "iteration": 32,
      "generations": 7,
      "best_fitness": 1.0,
      "perfect_found": true,
      "final_avg_fitness": 0.2073709095939994,
      "best_individual": {
        "expression": {
          "Individual": {
            "Head": "['@2', 'x0', '@1']",
            "Tail": "['@1', '@1', '@2', '@2']",
            "Weights": "[-0.008446116116494503, 0.9195329857762138, -0.7159147196956125, -0.3534280109977576, -1.4650566087226269, -2.024594361603917]",
            "Biases": "[0.3184444727367386, 1.9360739795074686, -1.3658932803429662]"
          }
        },
        "fitness": 1.0
      }
    },
    {
      "iteration": 33,
      "generations": 122,
      "best_fitness": 1.0,
      "perfect_found": true,
      "final_avg_fitness": 0.1563873777669796,
      "best_individual": {
        "expression": {
          "Individual": {
            "Head": "['@2', 'x0', '@1']",
            "Tail": "['@2', '@2', 'x0', '@2']",
            "Weights": "[1.8744310491109648, 0.017507911251069437, 0.229724284599286, -1.3507948677310166, 0.07630199789138303, -0.4660777552440407]",
            "Biases": "[0.12232620457887097, -0.1492770072803353, 0.08866036468744655]"
          }
        },
        "fitness": 1.0
      }
    },
    {
      "iteration": 34,
      "generations": 10,
      "best_fitness": 1.0,
      "perfect_found": true,
      "final_avg_fitness": 0.11397912788391114,
      "best_individual": {
        "expression": {
          "Individual": {
            "Head": "['@2', 'x0', '@1']",
            "Tail": "['@1', '@1', '@1', '@1']",
            "Weights": "[0.5851235761633523, -1.4504704818926315, -1.0647111679096308, 0.2585347464648209, -1.6799289723006745, -0.7844739315185536]",
            "Biases": "[0.3805719993217706, -0.10227158052554915, -0.1256523726203161]"
          }
        },
        "fitness": 1.0
      }
    },
    {
      "iteration": 35,
      "generations": 24,
      "best_fitness": 1.0,
      "perfect_found": true,
      "final_avg_fitness": 0.11956764079700224,
      "best_individual": {
        "expression": {
          "Individual": {
            "Head": "['@2', 'x0', '@1']",
            "Tail": "['@0', '@2', 'x0', '@2']",
            "Weights": "[2.5174283322268, -1.2452740317408109, 0.6986067229885665, -0.5643844346202751, -1.0734416813080403, 0.03682004562757618]",
            "Biases": "[0.23548698121336087, 0.10934075503137256, 0.8061425970883617]"
          }
        },
        "fitness": 1.0
      }
    },
    {
      "iteration": 36,
      "generations": 220,
      "best_fitness": 0.999999410165799,
      "perfect_found": true,
      "final_avg_fitness": 0.16016415619915983,
      "best_individual": {
        "expression": {
          "Individual": {
            "Head": "['subtract', 'add', 'x0']",
            "Tail": "['@2', '@2', 'x0', '@1']",
            "Weights": "[1.596239566910414, -0.0004981745997044017, -1.2883867391862933, 1.9151980150688095, 0.1665409249549754, -1.4909818081189314]",
            "Biases": "[-0.34787272864014857, 0.21715830597889413, 0.7838813109238691]"
          }
        },
        "fitness": 0.999999410165799
      }
    },
    {
      "iteration": 37,
      "generations": 1,
      "best_fitness": 1.0,
      "perfect_found": true,
      "final_avg_fitness": 0.1100126023888588,
      "best_individual": {
        "expression": {
          "Individual": {
            "Head": "['@2', 'x0', '@1']",
            "Tail": "['@2', '@0', '@0', '@1']",
            "Weights": "[0.22232859832759833, 0.3870001685279446, -0.45612604557348846, 1.6866819660594794, -0.4339564203205279, -2.312581804966033]",
            "Biases": "[-0.980764597745593, -2.0703804698578274, -0.8569011933531003]"
          }
        },
        "fitness": 1.0
      }
    },
    {
      "iteration": 38,
      "generations": 97,
      "best_fitness": 1.0,
      "perfect_found": true,
      "final_avg_fitness": 0.14705580057628687,
      "best_individual": {
        "expression": {
          "Individual": {
            "Head": "['@2', 'x0', '@1']",
            "Tail": "['@1', 'x0', '@1', '@2']",
            "Weights": "[0.05243527259602804, -2.2246007087340014, 0.8277094794015395, 1.5513911842068453, 2.613531025969356, -2.180232319992623]",
            "Biases": "[-0.39609988435286797, 0.14345176379380375, -0.7710943663401814]"
          }
        },
        "fitness": 1.0
      }
    },
    {
      "iteration": 39,
      "generations": 81,
      "best_fitness": 0.9999990964661265,
      "perfect_found": true,
      "final_avg_fitness": 0.2327276751627469,
      "best_individual": {
        "expression": {
          "Individual": {
            "Head": "['not_f', 'subtract', 'x0']",
            "Tail": "['@2', '@1', '@0', 'x0']",
            "Weights": "[0.6956772272649157, -0.000846358643560953, 1.4373077030103523, -0.04958271701168915, -0.14728100567373198, -0.32431700847948985]",
            "Biases": "[-1.1931170553965706, -0.28383364665320987, 0.11617104660910423]"
          }
        },
        "fitness": 0.9999990964661265
      }
    },
    {
      "iteration": 40,
      "generations": 3,
      "best_fitness": 1.0,
      "perfect_found": true,
      "final_avg_fitness": 0.04376848196983337,
      "best_individual": {
        "expression": {
          "Individual": {
            "Head": "['@2', 'x0', '@1']",
            "Tail": "['x0', '@1', '@2', '@1']",
            "Weights": "[-0.2794451007389164, -1.4052989053536393, -0.6642665370210337, -0.8003472012830181, -0.4323068756163223, -0.17234346708394144]",
            "Biases": "[1.0609499525057302, 0.16057506325801793, -0.04841142706395571]"
          }
        },
        "fitness": 1.0
      }
    },
    {
      "iteration": 41,
      "generations": 158,
      "best_fitness": 0.9999991717491525,
      "perfect_found": true,
      "final_avg_fitness": 0.23571191117489185,
      "best_individual": {
        "expression": {
          "Individual": {
            "Head": "['not_f', 'subtract', 'x0']",
            "Tail": "['@2', '@2', 'x0', '@2']",
            "Weights": "[1.1572508792282705, -0.0002092166991263509, 0.863747125813462, -0.42507219260695406, -0.8124578154345221, -5.014516292906968]",
            "Biases": "[1.4250258134003548, 2.0993436401094714, -0.8841057217913728]"
          }
        },
        "fitness": 0.9999991717491525
      }
    },
    {
      "iteration": 42,
      "generations": 145,
      "best_fitness": 1.0,
      "perfect_found": true,
      "final_avg_fitness": 0.16873501743607267,
      "best_individual": {
        "expression": {
          "Individual": {
            "Head": "['@2', 'x0', '@1']",
            "Tail": "['@2', 'x0', 'x0', 'x0']",
            "Weights": "[0.36743161301469235, 3.4821300244200146e-05, 3.0232273963358582, 0.7537843839203068, -2.4275407623794334, 2.141559501666409]",
            "Biases": "[-0.25472215800121295, -2.647116739927039, 0.051533956626371474]"
          }
        },
        "fitness": 1.0
      }
    },
    {
      "iteration": 43,
      "generations": 5,
      "best_fitness": 1.0,
      "perfect_found": true,
      "final_avg_fitness": 0.1482250404059887,
      "best_individual": {
        "expression": {
          "Individual": {
            "Head": "['@2', 'x0', '@1']",
            "Tail": "['x0', '@2', 'x0', '@1']",
            "Weights": "[0.05544731202687328, -1.7138919417462426, -0.31469059639901936, 0.4321930380370566, 1.1774642085311733, -0.03843506652219199]",
            "Biases": "[-0.08176164538751332, -0.4510115686189262, 0.4059270220482619]"
          }
        },
        "fitness": 1.0
      }
    },
    {
      "iteration": 44,
      "generations": 11,
      "best_fitness": 1.0,
      "perfect_found": true,
      "final_avg_fitness": 0.16177770357578994,
      "best_individual": {
        "expression": {
          "Individual": {
            "Head": "['@2', 'x0', '@1']",
            "Tail": "['x0', 'x0', '@1', 'x0']",
            "Weights": "[0.7366898255054533, -0.8440822012848406, 0.8559879991749095, 1.3219676824102211, -0.3876303912468448, -1.3429422639330475]",
            "Biases": "[2.08801547712034, 0.06374685807571225, -1.4924223135499162]"
          }
        },
        "fitness": 1.0
      }
    },
    {
      "iteration": 45,
      "generations": 2,
      "best_fitness": 1.0,
      "perfect_found": true,
      "final_avg_fitness": 0.08428754580020904,
      "best_individual": {
        "expression": {
          "Individual": {
            "Head": "['@2', 'x0', '@1']",
            "Tail": "['x0', '@0', 'x0', 'x0']",
            "Weights": "[0.8965417862040899, 1.578899555743999, 0.8333155297432333, -0.8859178807807198, 0.18629292940285058, 1.1573769440963577]",
            "Biases": "[-0.20181876284002828, 0.5349199021377079, 1.907199583330564]"
          }
        },
        "fitness": 1.0
      }
    },
    {
      "iteration": 46,
      "generations": 2,
      "best_fitness": 1.0,
      "perfect_found": true,
      "final_avg_fitness": 0.07864723655581474,
      "best_individual": {
        "expression": {
          "Individual": {
            "Head": "['@2', 'x0', '@1']",
            "Tail": "['x0', 'x0', 'x0', 'x0']",
            "Weights": "[0.218076864644553, 0.6369984577365786, 1.547551228792768, -0.8888640576689865, -1.9319869879850224, -0.08222993653811765]",
            "Biases": "[1.2998056710480048, -0.17988067556500556, 1.432463228937836]"
          }
        },
        "fitness": 1.0
      }
    },
    {
      "iteration": 47,
      "generations": 286,
      "best_fitness": 1.0,
      "perfect_found": true,
      "final_avg_fitness": 0.11928735083900392,
      "best_individual": {
        "expression": {
          "Individual": {
            "Head": "['@2', 'x0', '@1']",
            "Tail": "['@2', 'x0', '@1', '@1']",
            "Weights": "[8.086946572304829, -3.572248231877057, 1.8313076803207804, 0.039100934187364524, 0.1483969562610303, 0.22655066742069624]",
            "Biases": "[-0.5592210230103238, 1.0452943894225686, 0.6171661459026587]"
          }
        },
        "fitness": 1.0
      }
    },
    {
      "iteration": 48,
      "generations": 2,
      "best_fitness": 1.0,
      "perfect_found": true,
      "final_avg_fitness": 0.08651588892936707,
      "best_individual": {
        "expression": {
          "Individual": {
            "Head": "['@2', 'x0', '@1']",
            "Tail": "['@2', '@2', '@1', '@1']",
            "Weights": "[-0.2988839627514671, 0.5963210541168564, 1.519399337195836, -0.801328482217592, 0.7730467626926584, -0.7996874266868028]",
            "Biases": "[-0.05657734052050586, -0.8128511978694981, 1.1442793492597376]"
          }
        },
        "fitness": 1.0
      }
    },
    {
      "iteration": 49,
      "generations": 180,
      "best_fitness": 1.0,
      "perfect_found": true,
      "final_avg_fitness": 0.22717952947976847,
      "best_individual": {
        "expression": {
          "Individual": {
            "Head": "['@2', 'x0', '@1']",
            "Tail": "['x0', '@2', 'x0', '@2']",
            "Weights": "[-0.7647958895810703, 0.2370086745455417, 0.31180763216014573, -1.8578579596383475, -0.7261377905245987, -1.4967143008070514]",
            "Biases": "[-2.616426473562625, -3.392598550685822, 10.854150969407797]"
          }
        },
        "fitness": 1.0
      }
    },
    {
      "iteration": 50,
      "generations": 1,
      "best_fitness": 1.0,
      "perfect_found": true,
      "final_avg_fitness": 0.24227224564552308,
      "best_individual": {
        "expression": {
          "Individual": {
            "Head": "['@2', 'x0', '@1']",
            "Tail": "['@2', '@1', 'x0', 'x0']",
            "Weights": "[-1.241956926378402, 0.24693552196284144, -1.2163065235371802, 0.47821458780228127, 0.9136901465119079, -0.17300479546121647]",
            "Biases": "[-0.5346269927668342, -0.4759602288596439, -0.10645930317338975]"
          }
        },
        "fitness": 1.0
      }
    },
    {
      "iteration": 51,
      "generations": 2,
      "best_fitness": 1.0,
      "perfect_found": true,
      "final_avg_fitness": 0.03169078588485718,
      "best_individual": {
        "expression": {
          "Individual": {
            "Head": "['@2', 'x0', '@1']",
            "Tail": "['@2', 'x0', '@0', 'x0']",
            "Weights": "[-1.9673968354643514, -1.6894548807919176, 0.042310043937303046, -0.7606981905617761, -0.5344263864373875, -0.34247752388941266]",
            "Biases": "[-0.5496462265851766, -0.03727139668258647, -1.6494519597333528]"
          }
        },
        "fitness": 1.0
      }
    },
    {
      "iteration": 52,
      "generations": 110,
      "best_fitness": 1.0,
      "perfect_found": true,
      "final_avg_fitness": 0.24853534222341114,
      "best_individual": {
        "expression": {
          "Individual": {
            "Head": "['@2', 'x0', '@1']",
            "Tail": "['@0', '@2', '@1', '@0']",
            "Weights": "[-1.0230802012909948, -0.6449942486602437, 0.17405267814985687, -0.8879492722664707, 0.867675751403664, -0.05544533864683517]",
            "Biases": "[0.6042522313201023, 0.3002664897579154, 0.9050441563013666]"
          }
        },
        "fitness": 1.0
      }
    },
    {
      "iteration": 53,
      "generations": 74,
      "best_fitness": 1.0,
      "perfect_found": true,
      "final_avg_fitness": 0.23423595985982684,
      "best_individual": {
        "expression": {
          "Individual": {
            "Head": "['@2', 'x0', '@1']",
            "Tail": "['@0', 'x0', 'x0', 'x0']",
            "Weights": "[-0.8733142859622921, 0.2509514252800279, 1.0731199716238755, 1.3107438301194037, -3.272267791259386, 0.4552050584193441]",
            "Biases": "[-0.8936622895537447, 0.6738211155326878, 1.0315158308946113]"
          }
        },
        "fitness": 1.0
      }
    },
    {
      "iteration": 54,
      "generations": 4,
      "best_fitness": 1.0,
      "perfect_found": true,
      "final_avg_fitness": 0.07470878612995148,
      "best_individual": {
        "expression": {
          "Individual": {
            "Head": "['@2', 'x0', '@1']",
            "Tail": "['@1', '@2', '@2', 'x0']",
            "Weights": "[-0.1327011233965542, -2.0443979202420315, -1.3506566410109926, 0.41967999398289646, 0.4891025001355333, -1.965125354987518]",
            "Biases": "[0.5001084668934189, -1.0867475327292062, -0.18506719820931206]"
          }
        },
        "fitness": 1.0
      }
    },
    {
      "iteration": 55,
      "generations": 145,
      "best_fitness": 0.9999991764220226,
      "perfect_found": true,
      "final_avg_fitness": 0.18291747048111096,
      "best_individual": {
        "expression": {
          "Individual": {
            "Head": "['not_f', 'subtract', 'x0']",
            "Tail": "['@2', '@0', '@2', '@2']",
            "Weights": "[-0.5512479384441716, -0.0005961925324465813, -1.81559489816961, -0.9629703505993713, 0.4850324908503826, -1.982496516685679]",
            "Biases": "[-0.37176892250094923, -1.1386629624974165, -0.9799636565641614]"
          }
        },
        "fitness": 0.9999991764220226
      }
    },
    {
      "iteration": 56,
      "generations": 1,
      "best_fitness": 1.0,
      "perfect_found": true,
      "final_avg_fitness": 0.020410164833068848,
      "best_individual": {
        "expression": {
          "Individual": {
            "Head": "['@2', 'x0', '@1']",
            "Tail": "['@2', 'x0', '@1', '@1']",
            "Weights": "[-1.0126360457060737, -0.30989138676342115, 0.5979482612889454, 1.8748863093948, -0.11094865975720315, -0.3290196067024254]",
            "Biases": "[0.5558912569500144, -0.14128485908280794, -1.5729759274026487]"
          }
        },
        "fitness": 1.0
      }
    },
    {
      "iteration": 57,
      "generations": 2,
      "best_fitness": 1.0,
      "perfect_found": true,
      "final_avg_fitness": 0.052867914855480196,
      "best_individual": {
        "expression": {
          "Individual": {
            "Head": "['@2', 'x0', '@1']",
            "Tail": "['@0', '@1', '@1', '@0']",
            "Weights": "[-0.38195601670988183, 1.115277876004039, -1.7983335161451333, 0.77154900181523, 1.7282831056605825, -0.5028335062168765]",
            "Biases": "[0.12071746829144736, 1.098067480348877, 0.9821744612334162]"
          }
        },
        "fitness": 1.0
      }
    },
    {
      "iteration": 58,
      "generations": 173,
      "best_fitness": 1.0,
      "perfect_found": true,
      "final_avg_fitness": 0.24860127197234944,
      "best_individual": {
        "expression": {
          "Individual": {
            "Head": "['@2', 'x0', '@1']",
            "Tail": "['@2', '@0', '@0', '@1']",
            "Weights": "[1.2339519171006164, 0.3310169663396133, -0.2193044267440586, -0.3462418607548414, 0.6339842319308153, -0.539425560551474]",
            "Biases": "[-0.4847987469510811, 1.316667036747709, 2.1703361197724904]"
          }
        },
        "fitness": 1.0
      }
    },
    {
      "iteration": 59,
      "generations": 2,
      "best_fitness": 1.0,
      "perfect_found": true,
      "final_avg_fitness": 0.04078855639696121,
      "best_individual": {
        "expression": {
          "Individual": {
            "Head": "['@2', 'x0', '@1']",
            "Tail": "['x0', 'x0', 'x0', '@2']",
            "Weights": "[-0.047130695076393087, -0.9251725364537721, -0.4872065902255598, -0.8200244182140213, -0.5893432707404773, 0.9062638711041507]",
            "Biases": "[-0.5665559601745094, -0.5936332535880049, 1.476282865361327]"
          }
        },
        "fitness": 1.0
      }
    },
    {
      "iteration": 60,
      "generations": 11,
      "best_fitness": 1.0,
      "perfect_found": true,
      "final_avg_fitness": 0.18224387615313753,
      "best_individual": {
        "expression": {
          "Individual": {
            "Head": "['@2', 'x0', '@1']",
            "Tail": "['@1', '@0', '@1', 'x0']",
            "Weights": "[0.4212787791158399, -0.484820496200651, -0.4673772384543049, 0.7100095739878683, -0.7906964117549321, -0.2908162775649796]",
            "Biases": "[-0.591751099177358, 0.4162482824066094, -1.621317173057996]"
          }
        },
        "fitness": 1.0
      }
    },
    {
      "iteration": 61,
      "generations": 4,
      "best_fitness": 1.0,
      "perfect_found": true,
      "final_avg_fitness": 0.16614050620794296,
      "best_individual": {
        "expression": {
          "Individual": {
            "Head": "['@2', 'x0', '@1']",
            "Tail": "['x0', '@0', '@2', '@2']",
            "Weights": "[0.381140425729722, 0.6711842632762592, 0.5854766354087912, 0.9655343171417219, 0.07530265014928561, 0.03250932545335068]",
            "Biases": "[-0.058852907828458756, 0.3240210882976371, -0.07709064553780624]"
          }
        },
        "fitness": 1.0
      }
    },
    {
      "iteration": 62,
      "generations": 1,
      "best_fitness": 1.0,
      "perfect_found": true,
      "final_avg_fitness": 0.11892408412694931,
      "best_individual": {
        "expression": {
          "Individual": {
            "Head": "['@2', 'x0', '@1']",
            "Tail": "['@2', '@2', '@1', '@0']",
            "Weights": "[-0.826066185845216, 1.5851299389959328, -0.05834809035114672, 0.7086340428777511, -0.1771610162346341, 0.0793635515121533]",
            "Biases": "[-0.7901662539601858, -0.6603542903790106, 1.0383353534007955]"
          }
        },
        "fitness": 1.0
      }
    },
    {
      "iteration": 63,
      "generations": 2,
      "best_fitness": 1.0,
      "perfect_found": true,
      "final_avg_fitness": 0.02626221752166748,
      "best_individual": {
        "expression": {
          "Individual": {
            "Head": "['@2', 'x0', '@1']",
            "Tail": "['@1', 'x0', '@1', '@0']",
            "Weights": "[-0.6467754597328359, 0.30437900183958133, -0.040681839217480684, 0.6044642466459645, -0.49624950927006334, 0.18891393788981525]",
            "Biases": "[-1.8591368226326854, -0.16578204991141063, 1.4677615174145457]"
          }
        },
        "fitness": 1.0
      }
    },
    {
      "iteration": 64,
      "generations": 1,
      "best_fitness": 1.0,
      "perfect_found": true,
      "final_avg_fitness": 0.2391609036922455,
      "best_individual": {
        "expression": {
          "Individual": {
            "Head": "['@2', 'x0', '@1']",
            "Tail": "['x0', 'x0', '@1', '@1']",
            "Weights": "[0.7806580741233164, 0.9703191967501675, 0.576219049016325, -0.674181994241029, 1.351458253434056, 0.6787974571883743]",
            "Biases": "[-0.1347980632519355, 0.25895198407210335, -2.659500027101611]"
          }
        },
        "fitness": 1.0
      }
    },
    {
      "iteration": 65,
      "generations": 6,
      "best_fitness": 1.0,
      "perfect_found": true,
      "final_avg_fitness": 0.17434388744831086,
      "best_individual": {
        "expression": {
          "Individual": {
            "Head": "['@2', 'x0', '@1']",
            "Tail": "['@1', '@0', '@1', 'x0']",
            "Weights": "[-0.9485988467967378, -0.6384208929692504, 3.2778532963230194, -0.892839983598493, -0.6829881132784501, 0.991907615732081]",
            "Biases": "[-0.9357243996556096, 0.2786333421736322, -0.499785785269348]"
          }
        },
        "fitness": 1.0
      }
    },
    {
      "iteration": 66,
      "generations": 175,
      "best_fitness": 0.9999992255801544,
      "perfect_found": true,
      "final_avg_fitness": 0.23409280184085401,
      "best_individual": {
        "expression": {
          "Individual": {
            "Head": "['add', 'subtract', 'x0']",
            "Tail": "['@2', '@2', 'x0', 'x0']",
            "Weights": "[0.733807436646542, 0.0002337721303072365, 0.772902223646785, -0.5889718454560487, 0.15044631721017962, -2.1815857914250523]",
            "Biases": "[-0.46815205550369016, 0.6336391417524785, 0.3082271603686828]"
          }
        },
        "fitness": 0.9999992255801544
      }
    },
    {
      "iteration": 67,
      "generations": 78,
      "best_fitness": 1.0,
      "perfect_found": true,
      "final_avg_fitness": 0.12668301046825944,
      "best_individual": {
        "expression": {
          "Individual": {
            "Head": "['@2', 'x0', '@1']",
            "Tail": "['@2', 'x0', 'x0', 'x0']",
            "Weights": "[2.9321282717271373, 0.06883266208389967, 3.2956309744662873, 0.02562588704532291, 0.1074462810386503, 1.4764206237961504]",
            "Biases": "[-2.1777165656543738, -2.3743814466175897, 0.9057331134246442]"
          }
        },
        "fitness": 1.0
      }
    },
    {
      "iteration": 68,
      "generations": 167,
      "best_fitness": 0.9999999719277533,
      "perfect_found": true,
      "final_avg_fitness": 0.19084074946951562,
      "best_individual": {
        "expression": {
          "Individual": {
            "Head": "['add', 'not_f', 'x0']",
            "Tail": "['@2', '@1', 'x0', '@2']",
            "Weights": "[1.9250047808580328, 0.00010650058837275659, -0.5194480432761752, -2.8195277024044954, 0.725577415609075, 0.10026755379729471]",
            "Biases": "[0.8201240992439183, -1.4263825128662388, -0.17625813404448956]"
          }
        },
        "fitness": 0.9999999719277533
      }
    },
    {
      "iteration": 69,
      "generations": 396,
      "best_fitness": 1.0,
      "perfect_found": true,
      "final_avg_fitness": 0.12530429955816363,
      "best_individual": {
        "expression": {
          "Individual": {
            "Head": "['@2', 'x0', '@1']",
            "Tail": "['@2', 'x0', '@2', '@0']",
            "Weights": "[14.647356175466436, 0.2161251934990986, -0.2937331704140162, 0.3866239275919869, -0.7765324563265644, 1.4727847850045022]",
            "Biases": "[0.7652919050755467, -0.9319687492689442, -2.985245575652135]"
          }
        },
        "fitness": 1.0
      }
    },
    {
      "iteration": 70,
      "generations": 1,
      "best_fitness": 1.0,
      "perfect_found": true,
      "final_avg_fitness": 0.1996636006832123,
      "best_individual": {
        "expression": {
          "Individual": {
            "Head": "['@2', 'x0', '@1']",
            "Tail": "['x0', '@2', '@2', '@1']",
            "Weights": "[-0.6532844557790449, 0.7485067789688078, 0.003623120906734632, -1.408056233906498, 0.3822978300213497, 0.45844783329058575]",
            "Biases": "[1.3817213323887694, -0.9719792586318855, 0.6873236534671437]"
          }
        },
        "fitness": 1.0
      }
    },
    {
      "iteration": 71,
      "generations": 4,
      "best_fitness": 1.0,
      "perfect_found": true,
      "final_avg_fitness": 0.20819971710443497,
      "best_individual": {
        "expression": {
          "Individual": {
            "Head": "['@2', 'x0', '@1']",
            "Tail": "['x0', '@0', 'x0', '@0']",
            "Weights": "[-0.10153638383673495, -0.6073545916085059, 2.0271844320445838, -1.3151704399727626, -0.6829881132784501, 0.8713407957654609]",
            "Biases": "[0.5386700430918996, 0.5077229208251903, -0.42440159299205327]"
          }
        },
        "fitness": 1.0
      }
    },
    {
      "iteration": 72,
      "generations": 6,
      "best_fitness": 1.0,
      "perfect_found": true,
      "final_avg_fitness": 0.16341221421957017,
      "best_individual": {
        "expression": {
          "Individual": {
            "Head": "['@2', 'x0', '@1']",
            "Tail": "['@2', 'x0', '@2', '@2']",
            "Weights": "[0.41739673634182073, -0.7683725936009828, 1.0853191641845197, 0.7143377450711407, -0.5674483757750235, 2.1592241497416875]",
            "Biases": "[0.10547155622131732, 0.14537497679035227, -0.37622225283438876]"
          }
        },
        "fitness": 1.0
      }
    },
    {
      "iteration": 73,
      "generations": 2,
      "best_fitness": 1.0,
      "perfect_found": true,
      "final_avg_fitness": 0.08972581017017364,
      "best_individual": {
        "expression": {
          "Individual": {
            "Head": "['@2', 'x0', '@1']",
            "Tail": "['x0', '@2', '@0', '@2']",
            "Weights": "[-0.23968805486119832, 1.2372392031198014, 0.6192869103950152, 0.26952182777732586, 0.7561842814932915, 0.9815593428007315]",
            "Biases": "[-0.30171817264619355, -0.4516272518524775, -0.8400651250078958]"
          }
        },
        "fitness": 1.0
      }
    },
    {
      "iteration": 74,
      "generations": 1,
      "best_fitness": 1.0,
      "perfect_found": true,
      "final_avg_fitness": 0.1757733781337738,
      "best_individual": {
        "expression": {
          "Individual": {
            "Head": "['@2', 'x0', '@1']",
            "Tail": "['@1', '@0', 'x0', '@0']",
            "Weights": "[0.7439169543842331, 0.24507700953466174, 0.9718021231087696, 0.08138387123866017, 0.3189699429868802, 0.725594380634981]",
            "Biases": "[-0.9807668788319593, 0.039422084673790395, 1.3745457949617463]"
          }
        },
        "fitness": 1.0
      }
    },
    {
      "iteration": 75,
      "generations": 1,
      "best_fitness": 1.0,
      "perfect_found": true,
      "final_avg_fitness": 0.036880718350410464,
      "best_individual": {
        "expression": {
          "Individual": {
            "Head": "['@2', 'x0', '@1']",
            "Tail": "['@1', '@1', '@0', '@2']",
            "Weights": "[0.6011154524769334, -0.47247209463876405, -0.38144034864922094, -1.5455565320104308, -0.7233974230457672, 3.122863244075913]",
            "Biases": "[0.20968812798830597, 0.9155164307302393, 0.4527940527351942]"
          }
        },
        "fitness": 1.0
      }
    },
    {
      "iteration": 76,
      "generations": 51,
      "best_fitness": 1.0,
      "perfect_found": true,
      "final_avg_fitness": 0.19713141509474372,
      "best_individual": {
        "expression": {
          "Individual": {
            "Head": "['@2', 'x0', '@1']",
            "Tail": "['@2', '@1', '@1', '@2']",
            "Weights": "[-0.6899012624640659, -0.0827772077722253, 1.2803373619189093, -0.15408762104850407, -0.7869428094781352, 0.9730232372843666]",
            "Biases": "[0.023829090553689126, -1.2360896263957177, 0.546801138499784]"
          }
        },
        "fitness": 1.0
      }
    },
    {
      "iteration": 77,
      "generations": 8,
      "best_fitness": 1.0,
      "perfect_found": true,
      "final_avg_fitness": 0.2188495320212096,
      "best_individual": {
        "expression": {
          "Individual": {
            "Head": "['@2', 'x0', '@1']",
            "Tail": "['@0', '@1', 'x0', '@0']",
            "Weights": "[-0.757908926104743, -0.15343544447583407, -0.9251932903317446, 1.0897752156514469, 0.47485327330885413, 0.11959082959954105]",
            "Biases": "[-0.38117289884374467, 0.21191163810232796, -1.1798206143275836]"
          }
        },
        "fitness": 1.0
      }
    },
    {
      "iteration": 78,
      "generations": 15,
      "best_fitness": 1.0,
      "perfect_found": true,
      "final_avg_fitness": 0.12451106585562229,
      "best_individual": {
        "expression": {
          "Individual": {
            "Head": "['@2', 'x0', '@1']",
            "Tail": "['@2', '@1', '@1', '@1']",
            "Weights": "[-0.1599252051433342, 1.7963462845703537, 0.3714456368060717, -0.08706243276069481, -0.806734696158403, -0.5095122754347136]",
            "Biases": "[-0.36530828661556636, 2.4253010189502486, -5.963288840404257]"
          }
        },
        "fitness": 1.0
      }
    },
    {
      "iteration": 79,
      "generations": 145,
      "best_fitness": 1.0,
      "perfect_found": true,
      "final_avg_fitness": 0.18096042043421767,
      "best_individual": {
        "expression": {
          "Individual": {
            "Head": "['@2', 'x0', '@1']",
            "Tail": "['@2', 'x0', '@1', '@1']",
            "Weights": "[0.21151585736511494, 0.8246067153435058, 0.051577002738588895, 0.4921108060256804, 1.2310077940809134, 1.4529745951977937]",
            "Biases": "[1.0928230986697756, 1.7984688707729304, 0.9290833572059838]"
          }
        },
        "fitness": 1.0
      }
    },
    {
      "iteration": 80,
      "generations": 23,
      "best_fitness": 1.0,
      "perfect_found": true,
      "final_avg_fitness": 0.2518057144987397,
      "best_individual": {
        "expression": {
          "Individual": {
            "Head": "['@2', 'x0', '@1']",
            "Tail": "['@1', '@1', '@2', 'x0']",
            "Weights": "[-0.12278051577151511, -1.4426037078807235, 0.18064525518073066, 1.2022347165592553, 0.0334392163130594, 0.5262029973741935]",
            "Biases": "[1.9038038187647728, 1.0470841028206046, 0.1594520848224746]"
          }
        },
        "fitness": 1.0
      }
    },
    {
      "iteration": 81,
      "generations": 1,
      "best_fitness": 1.0,
      "perfect_found": true,
      "final_avg_fitness": 0.236475328437984,
      "best_individual": {
        "expression": {
          "Individual": {
            "Head": "['@2', 'x0', '@1']",
            "Tail": "['@1', '@1', 'x0', '@1']",
            "Weights": "[0.03116013447570352, -0.3533934299723749, -1.913371540702943, -1.0358462706213387, 1.8540650682150368, 2.633029662216034]",
            "Biases": "[-1.617609665584524, 0.18185415728711607, -0.25388155068931806]"
          }
        },
        "fitness": 1.0
      }
    },
    {
      "iteration": 82,
      "generations": 114,
      "best_fitness": 0.9999998950018067,
      "perfect_found": true,
      "final_avg_fitness": 0.20426752158585948,
      "best_individual": {
        "expression": {
          "Individual": {
            "Head": "['not_f', 'add', 'x0']",
            "Tail": "['@2', 'x0', '@0', '@0']",
            "Weights": "[0.38892643082264466, 0.0001286476206475689, -2.5718199987932464, 0.6993997371948162, 3.2803050713814446, 2.0763403588163194]",
            "Biases": "[-1.8254848721880161, -2.1194271213179583, 0.27405870972736257]"
          }
        },
        "fitness": 0.9999998950018067
      }
    },
    {
      "iteration": 83,
      "generations": 3,
      "best_fitness": 1.0,
      "perfect_found": true,
      "final_avg_fitness": 0.024200214385986327,
      "best_individual": {
        "expression": {
          "Individual": {
            "Head": "['@2', 'x0', '@1']",
            "Tail": "['x0', 'x0', 'x0', 'x0']",
            "Weights": "[-0.1496401850154058, 0.17304161857207595, 0.9557139357610396, 0.6079568555935344, -0.15330969102710384, -0.999595397663189]",
            "Biases": "[0.28679206777804384, 0.6606556161248455, -0.6139332162412765]"
          }
        },
        "fitness": 1.0
      }
    },
    {
      "iteration": 84,
      "generations": 1,
      "best_fitness": 1.0,
      "perfect_found": true,
      "final_avg_fitness": 0.1388503782749176,
      "best_individual": {
        "expression": {
          "Individual": {
            "Head": "['@2', 'x0', '@1']",
            "Tail": "['@0', '@2', '@1', '@2']",
            "Weights": "[-0.6859111944957512, -0.36784339713863035, -2.0780442297773387, -1.7287303337560973, -1.120530624003927, 2.115540284799456]",
            "Biases": "[-0.47032855172205273, -0.6849143268242538, -1.2656998251496796]"
          }
        },
        "fitness": 1.0
      }
    },
    {
      "iteration": 85,
      "generations": 156,
      "best_fitness": 0.999999484156092,
      "perfect_found": true,
      "final_avg_fitness": 0.21034065724714718,
      "best_individual": {
        "expression": {
          "Individual": {
            "Head": "['add', 'not_f', 'x0']",
            "Tail": "['@2', '@2', '@2', '@0']",
            "Weights": "[1.9582305372810196, 0.00021074895713844377, -0.5108632935695796, -2.37186767086702, -1.0648654365535681, -0.9691214322831908]",
            "Biases": "[-2.778776101602633, 0.4173442027283618, 3.5821258096963846]"
          }
        },
        "fitness": 0.999999484156092
      }
    },
    {
      "iteration": 86,
      "generations": 11,
      "best_fitness": 1.0,
      "perfect_found": true,
      "final_avg_fitness": 0.16124701693281532,
      "best_individual": {
        "expression": {
          "Individual": {
            "Head": "['@2', 'x0', '@1']",
            "Tail": "['@0', '@1', '@1', '@0']",
            "Weights": "[-0.17163344753036944, -0.881569978285442, -0.5804117188262974, 0.9687203788768942, 2.2879780318609115, -0.8768198998199213]",
            "Biases": "[0.26437886473631456, 1.8400062494032023, -0.7320600585435101]"
          }
        },
        "fitness": 1.0
      }
    },
    {
      "iteration": 87,
      "generations": 25,
      "best_fitness": 1.0,
      "perfect_found": true,
      "final_avg_fitness": 0.2358606861185981,
      "best_individual": {
        "expression": {
          "Individual": {
            "Head": "['@2', 'x0', '@1']",
            "Tail": "['x0', '@0', '@1', 'x0']",
            "Weights": "[0.24311188880060655, 1.5122837252654242, -0.6798807291423141, -0.7492684387957768, -1.4128185613811126, -0.11878278979103984]",
            "Biases": "[-0.3728876724055152, -2.2807671480185854, 0.17255846539631184]"
          }
        },
        "fitness": 1.0
      }
    },
    {
      "iteration": 88,
      "generations": 3,
      "best_fitness": 1.0,
      "perfect_found": true,
      "final_avg_fitness": 0.07774595528841019,
      "best_individual": {
        "expression": {
          "Individual": {
            "Head": "['@2', 'x0', '@1']",
            "Tail": "['@1', 'x0', 'x0', 'x0']",
            "Weights": "[-0.6285916612807992, 0.5255151596343597, -0.8128440774926782, 1.7439880890820447, 0.06863420265141826, 0.3932465147705242]",
            "Biases": "[0.9351853846348787, 0.2978286521233317, 0.9467274156280612]"
          }
        },
        "fitness": 1.0
      }
    },
    {
      "iteration": 89,
      "generations": 1,
      "best_fitness": 1.0,
      "perfect_found": true,
      "final_avg_fitness": 0.208134192943573,
      "best_individual": {
        "expression": {
          "Individual": {
            "Head": "['@2', 'x0', '@1']",
            "Tail": "['@2', '@0', 'x0', '@2']",
            "Weights": "[-0.1733381236231799, 0.37925677882326786, -0.4425190009202252, 0.07888374339112231, -0.8395965654319184, -0.16281707536918066]",
            "Biases": "[0.2630280618483187, -1.4870471349635068, -2.2826350443589996]"
          }
        },
        "fitness": 1.0
      }
    },
    {
      "iteration": 90,
      "generations": 231,
      "best_fitness": 0.9999996951681283,
      "perfect_found": true,
      "final_avg_fitness": 0.21432117288661198,
      "best_individual": {
        "expression": {
          "Individual": {
            "Head": "['subtract', 'subtract', 'x0']",
            "Tail": "['x0', '@2', '@2', '@2']",
            "Weights": "[-0.5038330329518804, -0.3579405155285478, 0.7112214001419723, 1.9854143501214003, -1.5853069993652655, 1.1592507104303227]",
            "Biases": "[0.5523124770768242, 1.0988444901540737, -3.490709916595136]"
          }
        },
        "fitness": 0.9999996951681283
      }
    },
    {
      "iteration": 91,
      "generations": 176,
      "best_fitness": 0.9999991009783571,
      "perfect_found": true,
      "final_avg_fitness": 0.21258806289148197,
      "best_individual": {
        "expression": {
          "Individual": {
            "Head": "['not_f', 'add', 'x0']",
            "Tail": "['@2', '@0', '@2', 'x0']",
            "Weights": "[-0.6225516197411768, 0.0012801219770372484, 1.6065854793240217, 0.3955013822686622, 0.009840408304583426, -2.0966621926538167]",
            "Biases": "[-0.2068003976833139, -1.2785545020711808, 0.06377902397066473]"
          }
        },
        "fitness": 0.9999991009783571
      }
    },
    {
      "iteration": 92,
      "generations": 55,
      "best_fitness": 0.9999991741051986,
      "perfect_found": true,
      "final_avg_fitness": 0.2811377640835269,
      "best_individual": {
        "expression": {
          "Individual": {
            "Head": "['not_f', 'add', 'x0']",
            "Tail": "['@2', '@2', 'x0', '@0']",
            "Weights": "[1.7117037073615475, 0.0002309428653294726, -0.5841936073506685, -1.281037016040761, -2.6202616553177016, -1.948111705653055]",
            "Biases": "[-0.40442833062336214, 0.3451707055541484, -0.26546708172383326]"
          }
        },
        "fitness": 0.9999991741051986
      }
    },
    {
      "iteration": 93,
      "generations": 4,
      "best_fitness": 1.0,
      "perfect_found": true,
      "final_avg_fitness": 0.16464986264333129,
      "best_individual": {
        "expression": {
          "Individual": {
            "Head": "['@2', 'x0', '@1']",
            "Tail": "['x0', 'x0', '@2', '@1']",
            "Weights": "[-0.3068553178622956, -0.8873527580108123, -0.06842690765126741, 0.550330371299886, -0.2765451030294026, -0.2188685816083938]",
            "Biases": "[0.03703849812345553, 0.29675388243165124, -1.2455083778478973]"
          }
        },
        "fitness": 1.0
      }
    },
    {
      "iteration": 94,
      "generations": 4,
      "best_fitness": 1.0,
      "perfect_found": true,
      "final_avg_fitness": 0.13797804641723632,
      "best_individual": {
        "expression": {
          "Individual": {
            "Head": "['@2', 'x0', '@1']",
            "Tail": "['@0', '@2', '@2', '@2']",
            "Weights": "[0.4047040012508095, 0.26424566856609555, 0.9242578966219237, -0.6266879875912159, 0.7763458988222979, -1.8689802985031996]",
            "Biases": "[0.3356831014562597, -2.813576582003796, 0.0013862210880697112]"
          }
        },
        "fitness": 1.0
      }
    },
    {
      "iteration": 95,
      "generations": 328,
      "best_fitness": 1.0,
      "perfect_found": true,
      "final_avg_fitness": 0.2507821033592136,
      "best_individual": {
        "expression": {
          "Individual": {
            "Head": "['@2', 'x0', '@1']",
            "Tail": "['@2', 'x0', '@0', 'x0']",
            "Weights": "[2.313430311891491, 0.0006665096195017445, 0.43241279155103196, 0.025957925445745544, 2.0074454059563536, -0.5405906626582024]",
            "Biases": "[0.17972226448675674, 0.5102883136107509, 0.8933611215311235]"
          }
        },
        "fitness": 1.0
      }
    },
    {
      "iteration": 96,
      "generations": 12,
      "best_fitness": 1.0,
      "perfect_found": true,
      "final_avg_fitness": 0.2252634744271636,
      "best_individual": {
        "expression": {
          "Individual": {
            "Head": "['@2', 'x0', '@1']",
            "Tail": "['x0', 'x0', '@2', '@2']",
            "Weights": "[0.3149193764040868, -0.7591298397142714, 1.1416580833429602, -0.9364771955821335, 1.2810963500282653, -0.7931995465079444]",
            "Biases": "[-0.22590040140298184, 1.6508591507569446, -0.06702096533314056]"
          }
        },
        "fitness": 1.0
      }
    },
    {
      "iteration": 97,
      "generations": 12,
      "best_fitness": 1.0,
      "perfect_found": true,
      "final_avg_fitness": 0.22282793021202088,
      "best_individual": {
        "expression": {
          "Individual": {
            "Head": "['@2', 'x0', '@1']",
            "Tail": "['@1', '@0', '@2', '@2']",
            "Weights": "[-0.36525096758090103, 0.3331698426123924, 0.9041561958090986, -0.27386739768086354, 0.3245330141712752, 0.06307902145048885]",
            "Biases": "[-0.03904578157985272, 1.364146769506703, -1.5202315367679158]"
          }
        },
        "fitness": 1.0
      }
    },
    {
      "iteration": 98,
      "generations": 215,
      "best_fitness": 0.9999991154212466,
      "perfect_found": true,
      "final_avg_fitness": 0.18688369783393638,
      "best_individual": {
        "expression": {
          "Individual": {
            "Head": "['subtract', 'not_f', 'not_f']",
            "Tail": "['@2', 'x0', '@1', '@2']",
            "Weights": "[-0.4382430598470386, -0.00041893123308469477, 1.302949052686775, -1.7502765532690334, 1.924980489573671, 1.1448037576170351]",
            "Biases": "[-0.7410146267757748, 0.21278402188308954, 1.228508990423608]"
          }
        },
        "fitness": 0.9999991154212466
      }
    },
    {
      "iteration": 99,
      "generations": 7,
      "best_fitness": 1.0,
      "perfect_found": true,
      "final_avg_fitness": 0.26325650145113466,
      "best_individual": {
        "expression": {
          "Individual": {
            "Head": "['@2', 'x0', '@1']",
            "Tail": "['x0', '@1', '@1', '@2']",
            "Weights": "[-0.18637601148231184, -0.7728300053518278, 0.5708555948784182, -0.25146857867826833, -0.9534568887717153, 0.7281037842060308]",
            "Biases": "[-0.787220871941994, -0.502023349933141, 0.5371299688655254]"
          }
        },
        "fitness": 1.0
      }
    },
    {
      "iteration": 100,
      "generations": 7,
      "best_fitness": 1.0,
      "perfect_found": true,
      "final_avg_fitness": 0.18364724460244178,
      "best_individual": {
        "expression": {
          "Individual": {
            "Head": "['@2', 'x0', '@1']",
            "Tail": "['x0', '@0', '@1', '@1']",
            "Weights": "[-0.7070217446884383, 1.2837113895359833, 1.028080623578975, 0.29463727133123374, 3.4394991298074156, -1.514162289363615]",
            "Biases": "[-0.4554153089129071, -0.09963547104828333, -0.3036154256938687]"
          }
        },
        "fitness": 1.0
      }
    }
  ]
}