{
  "parameters": {
    "iterations": 100,
    "population_size": 250,
    "max_generations": 1000,
    "crossover_rate": 0.8,
    "mutation_rate": 0.25,
    "tournament_size": 2,
    "elitism_ratio": 0.04,
    "head_length": 3,
    "t1": 0,
    "t2": -1
  },
  "results": [
    {
      "iteration": 1,
      "generations": 42,
      "best_fitness": 0.9999980000252668,
      "perfect_found": true,
      "final_avg_fitness": 0.2773577603879033,
      "best_individual": {
        "expression": {
          "Individual": {
            "Head": "['multiply', 'not_f', '@1']",
            "Tail": "['x0', '@1', '@1', '@1']",
            "Weights": "[0.1575942767288232, -2.0201844518111636, 4.997608811277891, -2.204053388751796, 2.6621546451658897, 3.859912011326533]",
            "Biases": "[1.1992587393719605, 1.002017354224623, -4.580893477253377]"
          }
        },
        "fitness": 0.9999980000252668
      }
    },
    {
      "iteration": 2,
      "generations": 9,
      "best_fitness": 0.9999980000252668,
      "perfect_found": true,
      "final_avg_fitness": 0.2576151348572439,
      "best_individual": {
        "expression": {
          "Individual": {
            "Head": "['multiply', 'multiply', '@1']",
            "Tail": "['x0', 'x0', '@0', '@1']",
            "Weights": "[-1.9508934631597743, 1.2382803480132334, 2.0851908857500616, -2.5426364604931218, -0.4819690653057269, 0.060313207175128225]",
            "Biases": "[1.962086252483828, 1.5726632923443635, 3.0426319834892235]"
          }
        },
        "fitness": 0.9999980000252668
      }
    },
    {
      "iteration": 3,
      "generations": 31,
      "best_fitness": 0.9999980000252668,
      "perfect_found": true,
      "final_avg_fitness": 0.2666060160479526,
      "best_individual": {
        "expression": {
          "Individual": {
            "Head": "['multiply', 'add', '@1']",
            "Tail": "['x0', 'x0', '@1', '@1']",
            "Weights": "[-3.9031396298641017, 4.8051964020057465, 0.1997605502656309, 2.896729136805144, -4.246441513479835, -0.9555562197130677]",
            "Biases": "[0.4575144786987394, -2.10424967421909, 0.7825619219386436]"
          }
        },
        "fitness": 0.9999980000252668
      }
    },
    {
      "iteration": 4,
      "generations": 35,
      "best_fitness": 0.9999980000252668,
      "perfect_found": true,
      "final_avg_fitness": 0.2579315486232875,
      "best_individual": {
        "expression": {
          "Individual": {
            "Head": "['multiply', 'not_f', 'not_f']",
            "Tail": "['@2', 'x0', '@2', 'x0']",
            "Weights": "[2.286326963892196, 1.2560237402188736, 1.6514863269609243, 1.5184427612740878, 0.06284339857342713, 0.5634659433722732]",
            "Biases": "[-0.7766714283092102, -0.9104658680428546, 0.039596164600616435]"
          }
        },
        "fitness": 0.9999980000252668
      }
    },
    {
      "iteration": 5,
      "generations": 11,
      "best_fitness": 0.9999980000252668,
      "perfect_found": true,
      "final_avg_fitness": 0.26090966854865016,
      "best_individual": {
        "expression": {
          "Individual": {
            "Head": "['multiply', 'tanh2', 'multiply']",
            "Tail": "['@1', '@2', 'x0', 'x0']",
            "Weights": "[1.308230941386955, 1.4255227116362081, 0.008352188556492113, -2.909350209105486, 1.9745237222044483, -4.876076631488578]",
            "Biases": "[-0.2603527820387981, 0.6702330104513483, 0.4804347204879441]"
          }
        },
        "fitness": 0.9999980000252668
      }
    },
    {
      "iteration": 6,
      "generations": 51,
      "best_fitness": 0.9999980000252668,
      "perfect_found": true,
      "final_avg_fitness": 0.27237490789808155,
      "best_individual": {
        "expression": {
          "Individual": {
            "Head": "['relu', 'multiply', 'relu2']",
            "Tail": "['@2', 'x0', 'x0', '@2']",
            "Weights": "[0.403876044638799, 2.4743810935962736, -0.3140241821740587, 2.0712623388648983, 4.965482335706401, -0.6063369371103766]",
            "Biases": "[-2.0193991244711267, 0.9895914390078532, -2.007077312974861]"
          }
        },
        "fitness": 0.9999980000252668
      }
    },
    {
      "iteration": 7,
      "generations": 38,
      "best_fitness": 0.9999980000252668,
      "perfect_found": true,
      "final_avg_fitness": 0.27792051354333136,
      "best_individual": {
        "expression": {
          "Individual": {
            "Head": "['multiply', 'subtract', 'tanh']",
            "Tail": "['@2', '@2', 'x0', '@2']",
            "Weights": "[1.696360769914257, -2.821091146419523, 3.0118267300552426, 0.6371967189921115, -2.575216122823647, 5.726459458599841]",
            "Biases": "[-0.08018637076333557, -0.5584010945013844, 0.41759756615562243]"
          }
        },
        "fitness": 0.9999980000252668
      }
    },
    {
      "iteration": 8,
      "generations": 18,
      "best_fitness": 0.9999980000252668,
      "perfect_found": true,
      "final_avg_fitness": 0.26283064777925846,
      "best_individual": {
        "expression": {
          "Individual": {
            "Head": "['multiply', 'add', 'not_f']",
            "Tail": "['x0', '@2', 'x0', 'x0']",
            "Weights": "[4.075118689787441, -2.500106249011537, 1.4208674667130012, 1.4207869999354177, -3.935379359437392, 3.0768294423457982]",
            "Biases": "[0.6907108744122664, 0.22459099260435672, -3.8787356791539054]"
          }
        },
        "fitness": 0.9999980000252668
      }
    },
    {
      "iteration": 9,
      "generations": 5,
      "best_fitness": 0.9999980000252668,
      "perfect_found": true,
      "final_avg_fitness": 0.2557185634286725,
      "best_individual": {
        "expression": {
          "Individual": {
            "Head": "['multiply', 'not_f', 'subtract']",
            "Tail": "['@2', '@2', 'x0', '@1']",
            "Weights": "[-2.2635452592484064, 1.2925372014051868, -0.7873192541737275, -0.18652781150507458, 1.7991375090162687, 0.8640818150605372]",
            "Biases": "[0.055841477957209465, -1.1108528056513085, 0.9658404030419675]"
          }
        },
        "fitness": 0.9999980000252668
      }
    },
    {
      "iteration": 10,
      "generations": 17,
      "best_fitness": 0.9999980000252668,
      "perfect_found": true,
      "final_avg_fitness": 0.2761308613467197,
      "best_individual": {
        "expression": {
          "Individual": {
            "Head": "['multiply', 'multiply', '@1']",
            "Tail": "['x0', 'x0', '@2', '@1']",
            "Weights": "[2.1086101981756697, -1.5230111982523764, -3.2384966014893806, 0.8858916375001513, -2.07814373078803, -3.475918217581307]",
            "Biases": "[-0.13215196651961414, 0.6439770428191915, -1.0628574236898616]"
          }
        },
        "fitness": 0.9999980000252668
      }
    },
    {
      "iteration": 11,
      "generations": 28,
      "best_fitness": 0.9999980000252668,
      "perfect_found": true,
      "final_avg_fitness": 0.27661091360480256,
      "best_individual": {
        "expression": {
          "Individual": {
            "Head": "['multiply', 'not_f', '@1']",
            "Tail": "['x0', 'x0', 'x0', '@1']",
            "Weights": "[-1.855810474327337, 2.4931050106393213, 3.120900845267154, 0.6203716019530486, 2.574802257951898, 3.2870094106510996]",
            "Biases": "[0.44639010650613264, -0.26940811411306576, -1.795216083717955]"
          }
        },
        "fitness": 0.9999980000252668
      }
    },
    {
      "iteration": 12,
      "generations": 56,
      "best_fitness": 0.9999980000252668,
      "perfect_found": true,
      "final_avg_fitness": 0.27897715383917754,
      "best_individual": {
        "expression": {
          "Individual": {
            "Head": "['multiply', 'subtract', 'subtract']",
            "Tail": "['@2', '@2', 'x0', 'x0']",
            "Weights": "[3.9075702473219702, -3.271564637474966, 3.871678271976844, 0.14537255044629466, 4.613098830922632, 1.5444986331071258]",
            "Biases": "[0.045962666512636585, -0.40961731673312585, -1.710847263739863]"
          }
        },
        "fitness": 0.9999980000252668
      }
    },
    {
      "iteration": 13,
      "generations": 24,
      "best_fitness": 0.9999980000252668,
      "perfect_found": true,
      "final_avg_fitness": 0.27788719539975926,
      "best_individual": {
        "expression": {
          "Individual": {
            "Head": "['multiply', 'not_f', '@1']",
            "Tail": "['x0', '@2', '@1', '@1']",
            "Weights": "[-1.8030346335847716, 3.16461752366302, 2.0982262539982868, 0.023088285721974855, 1.0527556588653058, 0.9978305596021189]",
            "Biases": "[0.5573262018583733, -0.14512792280103548, -0.6650943972867746]"
          }
        },
        "fitness": 0.9999980000252668
      }
    },
    {
      "iteration": 14,
      "generations": 33,
      "best_fitness": 0.9999980000252668,
      "perfect_found": true,
      "final_avg_fitness": 0.28030286086170825,
      "best_individual": {
        "expression": {
          "Individual": {
            "Head": "['multiply', 'relu', '@1']",
            "Tail": "['x0', '@2', 'x0', 'x0']",
            "Weights": "[-3.3653120431961097, 0.3833650061299635, 3.545378858891114, -1.728442126020216, 0.41295770527401554, 7.635185619974958]",
            "Biases": "[0.6013819907089035, -1.7091295618810813, -1.32019133388241]"
          }
        },
        "fitness": 0.9999980000252668
      }
    },
    {
      "iteration": 15,
      "generations": 40,
      "best_fitness": 0.9999980000252668,
      "perfect_found": true,
      "final_avg_fitness": 0.2816169561022564,
      "best_individual": {
        "expression": {
          "Individual": {
            "Head": "['multiply', 'multiply', 'multiply']",
            "Tail": "['x0', 'x0', '@0', '@2']",
            "Weights": "[3.881572313163972, 2.0319776508569762, -2.792616825047342, 1.8078387474450148, -3.468820363115362, 0.6498201362915872]",
            "Biases": "[-6.491033716144984, 0.3581899226765984, -0.9870509001142689]"
          }
        },
        "fitness": 0.9999980000252668
      }
    },
    {
      "iteration": 16,
      "generations": 24,
      "best_fitness": 0.9999980000252668,
      "perfect_found": true,
      "final_avg_fitness": 0.2787299817525845,
      "best_individual": {
        "expression": {
          "Individual": {
            "Head": "['multiply', 'not_f', 'not_f']",
            "Tail": "['x0', '@1', 'x0', '@0']",
            "Weights": "[-1.909382516996848, -1.4768122863682847, -3.3786158712929235, 3.089002718905779, 2.0826934726774518, 2.344423568816657]",
            "Biases": "[4.678347648436936, -2.0327528221683333, -1.3703992236975124]"
          }
        },
        "fitness": 0.9999980000252668
      }
    },
    {
      "iteration": 17,
      "generations": 81,
      "best_fitness": 0.9999980000252668,
      "perfect_found": true,
      "final_avg_fitness": 0.28394752269152035,
      "best_individual": {
        "expression": {
          "Individual": {
            "Head": "['multiply', 'multiply', '@1']",
            "Tail": "['x0', 'x0', '@2', '@1']",
            "Weights": "[-1.0969634369696544, 2.1063690464959377, 2.8243199274977697, 5.8976048862159915, -3.2260875071816777, 1.9982093884333314]",
            "Biases": "[-0.2549071493143396, -4.185256066883601, -1.0254592938016427]"
          }
        },
        "fitness": 0.9999980000252668
      }
    },
    {
      "iteration": 18,
      "generations": 18,
      "best_fitness": 0.9999980000252668,
      "perfect_found": true,
      "final_avg_fitness": 0.2624581673977015,
      "best_individual": {
        "expression": {
          "Individual": {
            "Head": "['multiply', 'add', '@1']",
            "Tail": "['x0', 'x0', '@2', '@0']",
            "Weights": "[1.4981130238897333, -1.969454204475881, 0.6368885055749278, 5.637409335123239, -3.638671463383208, -0.8888443982463531]",
            "Biases": "[-1.4976213019929827, -2.1757419679928245, -0.42818010822845587]"
          }
        },
        "fitness": 0.9999980000252668
      }
    },
    {
      "iteration": 19,
      "generations": 58,
      "best_fitness": 0.9999980000252668,
      "perfect_found": true,
      "final_avg_fitness": 0.2644445322319688,
      "best_individual": {
        "expression": {
          "Individual": {
            "Head": "['not_f', 'multiply', 'multiply']",
            "Tail": "['@2', 'x0', 'x0', '@1']",
            "Weights": "[-1.0220572943285022, -1.1789211121152832, 0.7485581084929596, -2.8885780084099477, 4.167939519778408, -0.8251697694433351]",
            "Biases": "[-1.2136155089817509, -5.404278846780249, 1.4886769755945513]"
          }
        },
        "fitness": 0.9999980000252668
      }
    },
    {
      "iteration": 20,
      "generations": 20,
      "best_fitness": 0.9999980000252668,
      "perfect_found": true,
      "final_avg_fitness": 0.26749484049936106,
      "best_individual": {
        "expression": {
          "Individual": {
            "Head": "['multiply', 'add', '@1']",
            "Tail": "['@2', 'x0', '@0', '@1']",
            "Weights": "[4.352303612084077, -1.705315370200021, -0.4237316603599561, -8.138376404484047, 5.014648413076043, -3.146845496383813]",
            "Biases": "[2.10855961400353, 4.01476024008992, -1.763929005058218]"
          }
        },
        "fitness": 0.9999980000252668
      }
    },
    {
      "iteration": 21,
      "generations": 10,
      "best_fitness": 0.9999980000252668,
      "perfect_found": true,
      "final_avg_fitness": 0.25904287681804194,
      "best_individual": {
        "expression": {
          "Individual": {
            "Head": "['multiply', 'not_f', '@1']",
            "Tail": "['x0', '@2', '@2', '@1']",
            "Weights": "[0.837641333511653, -0.8328280067794267, -3.252125157993915, -2.7772237836525693, -1.2747759694945116, -1.3051133946211766]",
            "Biases": "[-0.061422467782493495, -1.7688400805624669, 0.047407437918570876]"
          }
        },
        "fitness": 0.9999980000252668
      }
    },
    {
      "iteration": 22,
      "generations": 32,
      "best_fitness": 0.9999980000252668,
      "perfect_found": true,
      "final_avg_fitness": 0.2636486156180907,
      "best_individual": {
        "expression": {
          "Individual": {
            "Head": "['multiply', 'not_f', 'not_f']",
            "Tail": "['x0', '@1', 'x0', 'x0']",
            "Weights": "[0.5416499813053779, -4.62773776950256, -4.028973662711632, -2.0375262919669064, -3.3890375044997887, 1.9010550522503622]",
            "Biases": "[0.43980863471610365, -1.7307515375722131, -1.244396710126949]"
          }
        },
        "fitness": 0.9999980000252668
      }
    },
    {
      "iteration": 23,
      "generations": 16,
      "best_fitness": 0.9999980000252668,
      "perfect_found": true,
      "final_avg_fitness": 0.2588798983590924,
      "best_individual": {
        "expression": {
          "Individual": {
            "Head": "['multiply', 'not_f', 'not_f']",
            "Tail": "['x0', '@1', '@1', 'x0']",
            "Weights": "[3.9816238598951212, -1.9033252429361298, 1.9326101563259412, -2.2745454453012144, -5.665535221475535, -0.28368624415048993]",
            "Biases": "[0.4895402002372619, -0.7395561513313229, 0.6161129432763126]"
          }
        },
        "fitness": 0.9999980000252668
      }
    },
    {
      "iteration": 24,
      "generations": 64,
      "best_fitness": 0.9999980000252668,
      "perfect_found": true,
      "final_avg_fitness": 0.27763902335827495,
      "best_individual": {
        "expression": {
          "Individual": {
            "Head": "['multiply', 'multiply', '@1']",
            "Tail": "['x0', 'x0', '@0', '@1']",
            "Weights": "[-3.382664192813337, 4.530295362914855, -2.0323595999032897, 9.475302077800444, 0.6166613762256197, 0.1468336676476628]",
            "Biases": "[-0.6968258806401727, 0.23246476036520025, 2.149747196268448]"
          }
        },
        "fitness": 0.9999980000252668
      }
    },
    {
      "iteration": 25,
      "generations": 22,
      "best_fitness": 0.9999980000252668,
      "perfect_found": true,
      "final_avg_fitness": 0.25996044659866413,
      "best_individual": {
        "expression": {
          "Individual": {
            "Head": "['not_f', 'multiply', 'not_f']",
            "Tail": "['@2', 'x0', '@2', '@1']",
            "Weights": "[2.2107737298421815, 1.9170036205022698, 3.4888213811883464, 5.465629588753089, -0.2970728863423956, -1.8561842853660726]",
            "Biases": "[1.7194490059451877, -1.2908852009493306, 2.7378968025364356]"
          }
        },
        "fitness": 0.9999980000252668
      }
    },
    {
      "iteration": 26,
      "generations": 67,
      "best_fitness": 0.9999980000252668,
      "perfect_found": true,
      "final_avg_fitness": 0.2766954081901123,
      "best_individual": {
        "expression": {
          "Individual": {
            "Head": "['tanh', 'multiply', 'relu']",
            "Tail": "['@2', 'x0', '@0', 'x0']",
            "Weights": "[2.2329158229044026, -1.252644298072381, 7.1557130960971325, 2.2267848892264177, -1.5113361297493035, 7.956352570162776]",
            "Biases": "[0.8755502385298712, 4.207968451656881, -0.9243993729320268]"
          }
        },
        "fitness": 0.9999980000252668
      }
    },
    {
      "iteration": 27,
      "generations": 15,
      "best_fitness": 0.9999980000252668,
      "perfect_found": true,
      "final_avg_fitness": 0.2663710819223249,
      "best_individual": {
        "expression": {
          "Individual": {
            "Head": "['multiply', 'relu', 'subtract']",
            "Tail": "['x0', '@1', '@1', '@1']",
            "Weights": "[-1.0103160878717372, -3.5352154889934493, 2.746191258560397, -1.1766721897712886, 1.010717627658767, 0.924124739580807]",
            "Biases": "[-1.3597854986006734, -1.3391219375601184, 1.0549403809375384]"
          }
        },
        "fitness": 0.9999980000252668
      }
    },
    {
      "iteration": 28,
      "generations": 11,
      "best_fitness": 0.9999980000252668,
      "perfect_found": true,
      "final_avg_fitness": 0.2638267835476038,
      "best_individual": {
        "expression": {
          "Individual": {
            "Head": "['multiply', 'multiply', 'not_f']",
            "Tail": "['x0', 'x0', '@1', '@0']",
            "Weights": "[2.2548356856455825, -1.2216142129537453, -2.9191267058258568, 2.9116834197695955, -1.6556399231038554, -0.810820572541874]",
            "Biases": "[0.8392292087912339, 5.012334094417887, -2.632996803075174]"
          }
        },
        "fitness": 0.9999980000252668
      }
    },
    {
      "iteration": 29,
      "generations": 63,
      "best_fitness": 0.9999980000252668,
      "perfect_found": true,
      "final_avg_fitness": 0.27687165677135117,
      "best_individual": {
        "expression": {
          "Individual": {
            "Head": "['multiply', 'relu2', 'not_f']",
            "Tail": "['@2', '@2', 'x0', '@2']",
            "Weights": "[3.1520341303955473, -2.787335590006324, -0.9656272410760479, 6.143997950467902, -2.1387554719312707, -2.567210110636399]",
            "Biases": "[0.38218088853725785, -0.2372997466127622, -1.5644596248926035]"
          }
        },
        "fitness": 0.9999980000252668
      }
    },
    {
      "iteration": 30,
      "generations": 4,
      "best_fitness": 0.9999980000252668,
      "perfect_found": true,
      "final_avg_fitness": 0.2595178595886892,
      "best_individual": {
        "expression": {
          "Individual": {
            "Head": "['multiply', 'subtract', 'multiply']",
            "Tail": "['x0', 'x0', '@0', '@2']",
            "Weights": "[1.6138609811389286, -0.28534147515280167, -0.09675366275331078, -2.22219071055605, -2.965096000850214, 2.105584401013367]",
            "Biases": "[0.18952846289171488, -0.8722315807160439, -0.8560466115224205]"
          }
        },
        "fitness": 0.9999980000252668
      }
    },
    {
      "iteration": 31,
      "generations": 127,
      "best_fitness": 0.9999980000252668,
      "perfect_found": true,
      "final_avg_fitness": 0.29228640159102254,
      "best_individual": {
        "expression": {
          "Individual": {
            "Head": "['relu', 'multiply', 'relu']",
            "Tail": "['@2', 'x0', '@0', '@0']",
            "Weights": "[10.78613144004732, 12.674544014741436, -3.145575432902079, 4.663943901012991, 8.405961823594104, -6.543730941433368]",
            "Biases": "[-0.8063656176133549, -1.6934797940532875, -3.1555418891105242]"
          }
        },
        "fitness": 0.9999980000252668
      }
    },
    {
      "iteration": 32,
      "generations": 21,
      "best_fitness": 0.9999980000252668,
      "perfect_found": true,
      "final_avg_fitness": 0.26127811479411617,
      "best_individual": {
        "expression": {
          "Individual": {
            "Head": "['multiply', 'multiply', '@1']",
            "Tail": "['x0', 'x0', '@2', '@2']",
            "Weights": "[-0.73150011181647, 3.6514216517872993, -1.5359012723684793, 4.059268582799715, 0.3942707800211228, -0.7023985268950981]",
            "Biases": "[-0.011936107980782151, 0.17786198078245163, 0.03334963793301554]"
          }
        },
        "fitness": 0.9999980000252668
      }
    },
    {
      "iteration": 33,
      "generations": 35,
      "best_fitness": 0.9999980000252668,
      "perfect_found": true,
      "final_avg_fitness": 0.27107013652171197,
      "best_individual": {
        "expression": {
          "Individual": {
            "Head": "['multiply', 'multiply', 'add']",
            "Tail": "['@0', '@1', 'x0', 'x0']",
            "Weights": "[1.5387490116465241, -1.3454348843301613, -5.330782058205593, 0.3497425046054763, -0.2213433460488372, 5.232904428849701]",
            "Biases": "[2.6896749281255166, -2.4079796325953873, -3.147157602305273]"
          }
        },
        "fitness": 0.9999980000252668
      }
    },
    {
      "iteration": 34,
      "generations": 57,
      "best_fitness": 0.9999980000252668,
      "perfect_found": true,
      "final_avg_fitness": 0.27274437152586145,
      "best_individual": {
        "expression": {
          "Individual": {
            "Head": "['multiply', 'sigmoid2', 'multiply']",
            "Tail": "['@1', 'x0', '@2', '@0']",
            "Weights": "[7.27696370570573, -2.4623804803988465, -0.17400874805558442, 2.8542219717091246, 1.5361505514690723, -3.4040681768888]",
            "Biases": "[1.3431768938611015, -0.9306754194643042, -1.2321568987420606]"
          }
        },
        "fitness": 0.9999980000252668
      }
    },
    {
      "iteration": 35,
      "generations": 71,
      "best_fitness": 0.9999980000252668,
      "perfect_found": true,
      "final_avg_fitness": 0.26965799262789125,
      "best_individual": {
        "expression": {
          "Individual": {
            "Head": "['multiply', 'subtract', '@1']",
            "Tail": "['x0', 'x0', '@0', '@0']",
            "Weights": "[-1.0841273158756928, 0.9370074743720032, -0.8506294739779634, 4.4231389134139105, -3.2951693077833135, -1.9015463318276908]",
            "Biases": "[-1.3624320433449706, 0.5880569101522186, -1.4458700940033937]"
          }
        },
        "fitness": 0.9999980000252668
      }
    },
    {
      "iteration": 36,
      "generations": 81,
      "best_fitness": 0.9999980000252668,
      "perfect_found": true,
      "final_avg_fitness": 0.28044865721760215,
      "best_individual": {
        "expression": {
          "Individual": {
            "Head": "['multiply', 'not_f', 'add']",
            "Tail": "['x0', '@1', '@1', '@1']",
            "Weights": "[6.0020786260656624, 1.9722994212126, -5.393114749648729, -2.8515253722360976, -0.6116590564984647, -0.44332514889989777]",
            "Biases": "[0.05843455267201675, -1.4329786456195917, 0.8560983921261132]"
          }
        },
        "fitness": 0.9999980000252668
      }
    },
    {
      "iteration": 37,
      "generations": 36,
      "best_fitness": 0.9999980000252668,
      "perfect_found": true,
      "final_avg_fitness": 0.27342360188082093,
      "best_individual": {
        "expression": {
          "Individual": {
            "Head": "['multiply', 'not_f', '@1']",
            "Tail": "['x0', '@0', 'x0', 'x0']",
            "Weights": "[-2.0619278882720327, 1.8093098785727728, -1.5095500168084177, -0.431996590076273, -1.3890987890782405, -2.454033973972151]",
            "Biases": "[0.41108427522836866, -1.3645992213515408, -2.0782654515517884]"
          }
        },
        "fitness": 0.9999980000252668
      }
    },
    {
      "iteration": 38,
      "generations": 66,
      "best_fitness": 0.9999980000252668,
      "perfect_found": true,
      "final_avg_fitness": 0.28104263196783996,
      "best_individual": {
        "expression": {
          "Individual": {
            "Head": "['multiply', 'multiply', 'tanh']",
            "Tail": "['@1', '@0', 'x0', '@1']",
            "Weights": "[-3.444765756653277, 6.505122020846149, -1.2742719638411217, 6.448448631316269, -0.9667730419425891, -1.1520463860078545]",
            "Biases": "[3.1076085326598983, 3.0591512957537352, 0.4491822731271473]"
          }
        },
        "fitness": 0.9999980000252668
      }
    },
    {
      "iteration": 39,
      "generations": 33,
      "best_fitness": 0.9999980000252668,
      "perfect_found": true,
      "final_avg_fitness": 0.2789135332243757,
      "best_individual": {
        "expression": {
          "Individual": {
            "Head": "['multiply', 'relu', 'add']",
            "Tail": "['x0', '@1', '@1', '@0']",
            "Weights": "[4.034131218609121, -0.485904175779835, 4.5742528123286625, -0.367751874802948, 2.7573132111716725, -6.040427950906799]",
            "Biases": "[0.9547554332996198, -0.2971580220670247, -3.226228170314452]"
          }
        },
        "fitness": 0.9999980000252668
      }
    },
    {
      "iteration": 40,
      "generations": 15,
      "best_fitness": 0.9999980000252668,
      "perfect_found": true,
      "final_avg_fitness": 0.26434629978731505,
      "best_individual": {
        "expression": {
          "Individual": {
            "Head": "['multiply', 'relu', '@1']",
            "Tail": "['x0', '@1', '@1', '@1']",
            "Weights": "[-1.0534442291594899, 2.1029762887282675, 2.143334617960186, -0.2943821319746524, 3.0596478472819277, 3.3675776373771957]",
            "Biases": "[0.6444869469947672, -0.6397687200519993, -0.4344496618365238]"
          }
        },
        "fitness": 0.9999980000252668
      }
    },
    {
      "iteration": 41,
      "generations": 43,
      "best_fitness": 0.9999980000252668,
      "perfect_found": true,
      "final_avg_fitness": 0.28186495176485027,
      "best_individual": {
        "expression": {
          "Individual": {
            "Head": "['multiply', 'multiply', 'relu2']",
            "Tail": "['@0', '@1', 'x0', 'x0']",
            "Weights": "[3.4580593941528788, -1.119941133866248, 0.8366930520613239, -1.4954484329727926, 0.9944821735439954, 2.43438236064368]",
            "Biases": "[0.26310826722502073, -1.550404168909301, -2.498115903918133]"
          }
        },
        "fitness": 0.9999980000252668
      }
    },
    {
      "iteration": 42,
      "generations": 58,
      "best_fitness": 0.9999980000252668,
      "perfect_found": true,
      "final_avg_fitness": 0.2902235731823084,
      "best_individual": {
        "expression": {
          "Individual": {
            "Head": "['multiply', 'add', '@1']",
            "Tail": "['x0', 'x0', '@0', '@2']",
            "Weights": "[2.8106655102817006, -0.6794386342421003, -4.697223031274325, 2.7134093532805212, -2.2597327340989306, -2.274071437776847]",
            "Biases": "[0.925356219792971, 1.092314841187911, 3.251579404412737]"
          }
        },
        "fitness": 0.9999980000252668
      }
    },
    {
      "iteration": 43,
      "generations": 18,
      "best_fitness": 0.9999980000252668,
      "perfect_found": true,
      "final_avg_fitness": 0.26393343977144595,
      "best_individual": {
        "expression": {
          "Individual": {
            "Head": "['multiply', 'add', 'multiply']",
            "Tail": "['x0', 'x0', '@1', '@1']",
            "Weights": "[1.9620425388566438, 0.9357837462410117, -1.9304558524000464, -1.0781485949828324, -0.6120160919719939, 2.7887292000143216]",
            "Biases": "[-1.0558254948824648, 2.5671340705569676, 1.6626267565706532]"
          }
        },
        "fitness": 0.9999980000252668
      }
    },
    {
      "iteration": 44,
      "generations": 21,
      "best_fitness": 0.9999980000252668,
      "perfect_found": true,
      "final_avg_fitness": 0.2648314096069998,
      "best_individual": {
        "expression": {
          "Individual": {
            "Head": "['multiply', 'multiply', 'add']",
            "Tail": "['@0', '@1', 'x0', 'x0']",
            "Weights": "[2.611259351236391, -1.562629684062589, 1.2668751187373228, -0.5225946282706231, 6.201347287774526, 1.3098221742036202]",
            "Biases": "[-1.1165081299756063, 4.9667053838866, -1.1476955347005284]"
          }
        },
        "fitness": 0.9999980000252668
      }
    },
    {
      "iteration": 45,
      "generations": 103,
      "best_fitness": 0.9999980000252668,
      "perfect_found": true,
      "final_avg_fitness": 0.2742309268886683,
      "best_individual": {
        "expression": {
          "Individual": {
            "Head": "['multiply', 'tanh', 'multiply']",
            "Tail": "['x0', '@0', '@2', '@1']",
            "Weights": "[2.5234684766486444, -8.516183568192558, -1.9880938603159222, -3.4596973881588267, 2.4032205627695307, -3.847142698960214]",
            "Biases": "[0.5730666065339843, 0.09126461332097446, -2.5548700724418376]"
          }
        },
        "fitness": 0.9999980000252668
      }
    },
    {
      "iteration": 46,
      "generations": 35,
      "best_fitness": 0.9999980000252668,
      "perfect_found": true,
      "final_avg_fitness": 0.27627300167240987,
      "best_individual": {
        "expression": {
          "Individual": {
            "Head": "['multiply', 'add', '@1']",
            "Tail": "['@2', 'x0', '@0', '@2']",
            "Weights": "[-1.1122379827358198, 2.6135165030277734, 0.2672936233663139, -4.005588924622697, 5.137835639637486, -0.09512087453769791]",
            "Biases": "[0.632128609462254, 2.09566213033587, -1.4668419820398253]"
          }
        },
        "fitness": 0.9999980000252668
      }
    },
    {
      "iteration": 47,
      "generations": 98,
      "best_fitness": 0.9999980000252668,
      "perfect_found": true,
      "final_avg_fitness": 0.27534314685626865,
      "best_individual": {
        "expression": {
          "Individual": {
            "Head": "['relu', 'multiply', 'multiply']",
            "Tail": "['@2', 'x0', 'x0', '@0']",
            "Weights": "[9.498917308308052, 2.349731140680522, -4.9032648136952455, 5.946306582398924, -1.118320519149845, -0.0204639693338865]",
            "Biases": "[-2.559911386381419, -1.3741278426494992, 0.43773656863685523]"
          }
        },
        "fitness": 0.9999980000252668
      }
    },
    {
      "iteration": 48,
      "generations": 4,
      "best_fitness": 0.9999980000252668,
      "perfect_found": true,
      "final_avg_fitness": 0.2553135093428048,
      "best_individual": {
        "expression": {
          "Individual": {
            "Head": "['multiply', 'not_f', 'subtract']",
            "Tail": "['@2', 'x0', 'x0', 'x0']",
            "Weights": "[-0.2505298680841939, -2.2074647253689212, 2.4510088736159923, 3.413204954024759, 0.5483829930597689, 0.6318078000967857]",
            "Biases": "[1.4692358320148966, -0.375624970945216, -1.1385231951458188]"
          }
        },
        "fitness": 0.9999980000252668
      }
    },
    {
      "iteration": 49,
      "generations": 15,
      "best_fitness": 0.9999980000252668,
      "perfect_found": true,
      "final_avg_fitness": 0.2674076898953895,
      "best_individual": {
        "expression": {
          "Individual": {
            "Head": "['multiply', 'subtract', '@1']",
            "Tail": "['@2', 'x0', 'x0', 'x0']",
            "Weights": "[-1.3721007579209796, 2.0686520080260933, -0.2049186499762996, 2.334410532541154, -2.7930096571685787, 0.6973299684159883]",
            "Biases": "[-0.18576667030034383, 0.5509945978059437, 1.8979105052460508]"
          }
        },
        "fitness": 0.9999980000252668
      }
    },
    {
      "iteration": 50,
      "generations": 33,
      "best_fitness": 0.9999980000252668,
      "perfect_found": true,
      "final_avg_fitness": 0.26412986559039736,
      "best_individual": {
        "expression": {
          "Individual": {
            "Head": "['multiply', 'multiply', 'add']",
            "Tail": "['@1', '@0', 'x0', 'x0']",
            "Weights": "[1.029209555346966, -3.196092791192728, -0.6231237261849087, 4.8076041657778426, -2.1183966869325084, 1.369912235294966]",
            "Biases": "[-1.692057744799363, 4.591867600356736, 0.2655986716844783]"
          }
        },
        "fitness": 0.9999980000252668
      }
    },
    {
      "iteration": 51,
      "generations": 22,
      "best_fitness": 0.9999980000252668,
      "perfect_found": true,
      "final_avg_fitness": 0.26901321128197886,
      "best_individual": {
        "expression": {
          "Individual": {
            "Head": "['not_f', 'multiply', 'relu']",
            "Tail": "['@2', 'x0', '@2', 'x0']",
            "Weights": "[-0.7152166799480187, -0.7052609156814484, 1.5377780339098195, 3.914999723970107, -1.5568184001608993, -1.0192962878215233]",
            "Biases": "[-2.2772968282959454, -0.20740701899040945, -1.295543441071985]"
          }
        },
        "fitness": 0.9999980000252668
      }
    },
    {
      "iteration": 52,
      "generations": 39,
      "best_fitness": 0.9999980000252668,
      "perfect_found": true,
      "final_avg_fitness": 0.2810462890674946,
      "best_individual": {
        "expression": {
          "Individual": {
            "Head": "['multiply', 'relu', 'multiply']",
            "Tail": "['x0', '@2', '@0', 'x0']",
            "Weights": "[-1.0911123627578716, 1.8138137985588558, 4.078076369925912, -1.3635027629642538, 2.7533332639819887, -2.5361452912305835]",
            "Biases": "[-0.40435811548984396, -1.8330646354806068, 0.3992437239542409]"
          }
        },
        "fitness": 0.9999980000252668
      }
    },
    {
      "iteration": 53,
      "generations": 13,
      "best_fitness": 0.9999980000252668,
      "perfect_found": true,
      "final_avg_fitness": 0.27950689502252457,
      "best_individual": {
        "expression": {
          "Individual": {
            "Head": "['multiply', 'multiply', 'tanh']",
            "Tail": "['x0', 'x0', '@1', '@2']",
            "Weights": "[1.8375203179706037, 0.6196504825214312, 4.174785845028333, -2.344383605069415, -0.2915996193976287, 0.8016232377117503]",
            "Biases": "[0.9198111139390371, 1.4711303088842178, -0.8529537489971024]"
          }
        },
        "fitness": 0.9999980000252668
      }
    },
    {
      "iteration": 54,
      "generations": 39,
      "best_fitness": 0.9999980000252668,
      "perfect_found": true,
      "final_avg_fitness": 0.27855801390138313,
      "best_individual": {
        "expression": {
          "Individual": {
            "Head": "['multiply', 'not_f', '@1']",
            "Tail": "['x0', '@2', '@1', '@2']",
            "Weights": "[-2.08304137007538, 1.6331165299033819, 8.21789148807704, -3.4598222134905714, 2.2458934044301575, -2.486858724674045]",
            "Biases": "[0.6163942073230291, -0.19595162148413936, 1.7030650254877844]"
          }
        },
        "fitness": 0.9999980000252668
      }
    },
    {
      "iteration": 55,
      "generations": 28,
      "best_fitness": 0.9999980000252668,
      "perfect_found": true,
      "final_avg_fitness": 0.29010164309796066,
      "best_individual": {
        "expression": {
          "Individual": {
            "Head": "['multiply', 'tanh2', '@1']",
            "Tail": "['x0', 'x0', '@2', 'x0']",
            "Weights": "[4.30736824236529, -1.672097897525218, -0.4140428610359631, -0.9834128771139199, -0.8520187484121426, 0.17981868873296059]",
            "Biases": "[0.19051512628385514, 0.32433654889587926, 2.1060674357756692]"
          }
        },
        "fitness": 0.9999980000252668
      }
    },
    {
      "iteration": 56,
      "generations": 125,
      "best_fitness": 0.9999980000252668,
      "perfect_found": true,
      "final_avg_fitness": 0.27519987849650873,
      "best_individual": {
        "expression": {
          "Individual": {
            "Head": "['multiply', 'multiply', 'add']",
            "Tail": "['x0', 'x0', '@1', 'x0']",
            "Weights": "[-2.474165078889226, 3.2202972147749813, -4.077232315884519, -1.4812196837971052, 1.674813461445595, -6.042577152303152]",
            "Biases": "[-3.2123635259182253, -0.36383618771431797, 1.0290884871214732]"
          }
        },
        "fitness": 0.9999980000252668
      }
    },
    {
      "iteration": 57,
      "generations": 15,
      "best_fitness": 0.9999980000252668,
      "perfect_found": true,
      "final_avg_fitness": 0.25838101658854973,
      "best_individual": {
        "expression": {
          "Individual": {
            "Head": "['multiply', 'not_f', 'not_f']",
            "Tail": "['x0', '@1', '@2', '@2']",
            "Weights": "[1.2199124185558208, 1.7257636778857777, -2.800969720340431, 2.4228887906888157, 0.5773155374215962, 1.4154387331247837]",
            "Biases": "[-1.0995061058563877, -2.046205319553247, 0.35205899395614115]"
          }
        },
        "fitness": 0.9999980000252668
      }
    },
    {
      "iteration": 58,
      "generations": 33,
      "best_fitness": 0.9999980000252668,
      "perfect_found": true,
      "final_avg_fitness": 0.26411945102807255,
      "best_individual": {
        "expression": {
          "Individual": {
            "Head": "['multiply', 'relu', 'not_f']",
            "Tail": "['@2', 'x0', '@1', '@0']",
            "Weights": "[2.2745937292635117, -2.369856235702439, 2.1043714696670155, 2.6653110824859727, -2.885886406254838, 1.8289895812792474]",
            "Biases": "[0.9906951710384472, -0.5313550664326165, 1.1489740527251384]"
          }
        },
        "fitness": 0.9999980000252668
      }
    },
    {
      "iteration": 59,
      "generations": 28,
      "best_fitness": 0.9999980000252668,
      "perfect_found": true,
      "final_avg_fitness": 0.27344735310152407,
      "best_individual": {
        "expression": {
          "Individual": {
            "Head": "['multiply', 'not_f', 'multiply']",
            "Tail": "['@2', 'x0', 'x0', 'x0']",
            "Weights": "[1.433218790955986, 1.22826654224068, 2.9253603633328034, -2.09368336324942, -1.364784470910191, 4.2303112018397]",
            "Biases": "[-0.04062283554719681, 1.0373921638465375, -0.7783458101881995]"
          }
        },
        "fitness": 0.9999980000252668
      }
    },
    {
      "iteration": 60,
      "generations": 44,
      "best_fitness": 0.9999980000252668,
      "perfect_found": true,
      "final_avg_fitness": 0.2871115638365385,
      "best_individual": {
        "expression": {
          "Individual": {
            "Head": "['multiply', 'relu2', 'multiply']",
            "Tail": "['x0', 'x0', '@2', '@0']",
            "Weights": "[0.44193796436567856, 0.7314999449500335, 4.600010884217275, 3.6282624618213077, -3.911862901892013, 3.779174404667481]",
            "Biases": "[0.05755129828327271, -0.40563104411950274, 0.5002099909694281]"
          }
        },
        "fitness": 0.9999980000252668
      }
    },
    {
      "iteration": 61,
      "generations": 42,
      "best_fitness": 0.9999980000252668,
      "perfect_found": true,
      "final_avg_fitness": 0.2775775461121267,
      "best_individual": {
        "expression": {
          "Individual": {
            "Head": "['multiply', 'multiply', 'subtract']",
            "Tail": "['@1', '@0', 'x0', 'x0']",
            "Weights": "[4.609663903801562, 2.882855636153868, 0.6298185419425477, -0.32457103377498137, -2.2308411249627667, 2.2545797144959954]",
            "Biases": "[-0.21420748287503943, -4.466927214648599, 2.7790163763703886]"
          }
        },
        "fitness": 0.9999980000252668
      }
    },
    {
      "iteration": 62,
      "generations": 33,
      "best_fitness": 0.9999980000252668,
      "perfect_found": true,
      "final_avg_fitness": 0.27377329673337747,
      "best_individual": {
        "expression": {
          "Individual": {
            "Head": "['multiply', 'multiply', '@1']",
            "Tail": "['x0', 'x0', 'x0', 'x0']",
            "Weights": "[-4.8567107712273, 1.2750448459328414, -6.188619758380316, 2.3495128320208827, 0.8243405806207944, -1.7551441092779136]",
            "Biases": "[0.2230535088197128, 1.2625017398433958, 3.9994183135784436]"
          }
        },
        "fitness": 0.9999980000252668
      }
    },
    {
      "iteration": 63,
      "generations": 35,
      "best_fitness": 0.9999980000252668,
      "perfect_found": true,
      "final_avg_fitness": 0.2761651631350498,
      "best_individual": {
        "expression": {
          "Individual": {
            "Head": "['multiply', 'multiply', '@1']",
            "Tail": "['x0', 'x0', 'x0', '@2']",
            "Weights": "[-2.608609466108062, 1.9157977057972748, 3.9240743755228205, -2.404786317801907, 1.6136974373778545, -1.5457299920762366]",
            "Biases": "[2.1234064684565888, 2.371118995360073, 0.06876706465933244]"
          }
        },
        "fitness": 0.9999980000252668
      }
    },
    {
      "iteration": 64,
      "generations": 49,
      "best_fitness": 0.9999980000252668,
      "perfect_found": true,
      "final_avg_fitness": 0.2754241000325915,
      "best_individual": {
        "expression": {
          "Individual": {
            "Head": "['multiply', 'tanh2', 'multiply']",
            "Tail": "['@2', '@1', 'x0', 'x0']",
            "Weights": "[-1.3343477281419165, 4.055790511636567, 3.6538023874937817, -0.4785944677224716, -1.8202759457572977, 1.9933792036161313]",
            "Biases": "[0.9754180602067597, -0.6604713373251321, 1.1810346151079134]"
          }
        },
        "fitness": 0.9999980000252668
      }
    },
    {
      "iteration": 65,
      "generations": 43,
      "best_fitness": 0.9999980000252668,
      "perfect_found": true,
      "final_avg_fitness": 0.2661928277738074,
      "best_individual": {
        "expression": {
          "Individual": {
            "Head": "['multiply', 'subtract', '@1']",
            "Tail": "['@1', 'x0', '@1', '@0']",
            "Weights": "[3.9353742952902575, -0.33951582445888673, -0.2486466911385355, 5.493949437782899, 0.5213576764641616, 0.4239039055508427]",
            "Biases": "[-0.526422937012335, 1.3307052861260953, -1.5259833519557646]"
          }
        },
        "fitness": 0.9999980000252668
      }
    },
    {
      "iteration": 66,
      "generations": 61,
      "best_fitness": 0.9999980000252668,
      "perfect_found": true,
      "final_avg_fitness": 0.27610262808234154,
      "best_individual": {
        "expression": {
          "Individual": {
            "Head": "['relu', 'multiply', 'add']",
            "Tail": "['@2', 'x0', 'x0', '@0']",
            "Weights": "[-0.830012598886684, -5.6677598119593435, -4.267682390714272, -0.6205718758348782, 2.5636013579696497, -1.8918111271942328]",
            "Biases": "[-2.712305342789951, -2.3900869723763147, -1.6965805878589602]"
          }
        },
        "fitness": 0.9999980000252668
      }
    },
    {
      "iteration": 67,
      "generations": 12,
      "best_fitness": 0.9999980000252668,
      "perfect_found": true,
      "final_avg_fitness": 0.26966429230178907,
      "best_individual": {
        "expression": {
          "Individual": {
            "Head": "['multiply', 'subtract', '@1']",
            "Tail": "['x0', 'x0', '@1', '@1']",
            "Weights": "[-2.466176262073663, 1.8790534097322111, 1.0822801938168722, -2.847493947523371, -5.368724420252791, 0.3214038495008563]",
            "Biases": "[1.3199768303387864, -1.8257213814546838, 3.8078141160873944]"
          }
        },
        "fitness": 0.9999980000252668
      }
    },
    {
      "iteration": 68,
      "generations": 27,
      "best_fitness": 0.9999980000252668,
      "perfect_found": true,
      "final_avg_fitness": 0.3053296936435911,
      "best_individual": {
        "expression": {
          "Individual": {
            "Head": "['multiply', 'subtract', '@1']",
            "Tail": "['@1', 'x0', '@0', '@0']",
            "Weights": "[-2.6269231182903683, 2.9605842102611897, -0.323878600287176, -2.8004385219980943, -4.335944853040766, 1.0863504403534994]",
            "Biases": "[-3.0945464702454752, -1.8287072390610215, 0.5601864177395207]"
          }
        },
        "fitness": 0.9999980000252668
      }
    },
    {
      "iteration": 69,
      "generations": 39,
      "best_fitness": 0.9999980000252668,
      "perfect_found": true,
      "final_avg_fitness": 0.26746415119661276,
      "best_individual": {
        "expression": {
          "Individual": {
            "Head": "['multiply', 'multiply', '@1']",
            "Tail": "['x0', 'x0', '@0', '@0']",
            "Weights": "[2.9650844661963864, -1.333925920035219, 3.042523598863511, 6.023968638752044, 1.624074591426178, 0.5399534798683474]",
            "Biases": "[1.0617658975637685, -3.2202962355572136, -0.3433644262482074]"
          }
        },
        "fitness": 0.9999980000252668
      }
    },
    {
      "iteration": 70,
      "generations": 11,
      "best_fitness": 0.9999980000252668,
      "perfect_found": true,
      "final_avg_fitness": 0.25825628702660774,
      "best_individual": {
        "expression": {
          "Individual": {
            "Head": "['not_f', 'multiply', 'relu']",
            "Tail": "['@2', 'x0', '@2', '@1']",
            "Weights": "[3.8983648300818885, -3.5626473777788785, -3.141365832635405, 2.5363991654395015, -0.21618875331913845, 5.547328249929849]",
            "Biases": "[-2.1126078171351224, -1.5193692524862583, -1.0585536645088593]"
          }
        },
        "fitness": 0.9999980000252668
      }
    },
    {
      "iteration": 71,
      "generations": 78,
      "best_fitness": 0.9999980000252668,
      "perfect_found": true,
      "final_avg_fitness": 0.2915046281990285,
      "best_individual": {
        "expression": {
          "Individual": {
            "Head": "['relu', 'multiply', 'not_f']",
            "Tail": "['@2', 'x0', 'x0', 'x0']",
            "Weights": "[6.279934738914049, 7.22266703632946, -6.1189422693615505, 5.105020288883304, 5.036459142301018, 0.07621610155661768]",
            "Biases": "[-0.30908879121934474, -0.38315845431396633, 2.2984600744967656]"
          }
        },
        "fitness": 0.9999980000252668
      }
    },
    {
      "iteration": 72,
      "generations": 20,
      "best_fitness": 0.9999980000252668,
      "perfect_found": true,
      "final_avg_fitness": 0.2748207170846783,
      "best_individual": {
        "expression": {
          "Individual": {
            "Head": "['multiply', 'multiply', '@1']",
            "Tail": "['x0', 'x0', '@0', '@1']",
            "Weights": "[0.9002814318970389, -3.49806828352097, -2.2346273569212287, -2.423110754437511, -0.6759610932026197, 0.48250405908982197]",
            "Biases": "[0.7438977308625707, -1.2393186161110137, -2.4704282488938216]"
          }
        },
        "fitness": 0.9999980000252668
      }
    },
    {
      "iteration": 73,
      "generations": 18,
      "best_fitness": 0.9999980000252668,
      "perfect_found": true,
      "final_avg_fitness": 0.2691907182748639,
      "best_individual": {
        "expression": {
          "Individual": {
            "Head": "['multiply', 'not_f', 'relu']",
            "Tail": "['x0', '@1', '@1', 'x0']",
            "Weights": "[1.1164337513589695, 1.1119629316539548, 2.7859327284281923, -2.5973805178764735, -0.991201494002634, 1.3622199870870595]",
            "Biases": "[-0.3250018409218622, -0.703232783127983, -0.8396209006772322]"
          }
        },
        "fitness": 0.9999980000252668
      }
    },
    {
      "iteration": 74,
      "generations": 12,
      "best_fitness": 0.9999980000252668,
      "perfect_found": true,
      "final_avg_fitness": 0.2611772385385358,
      "best_individual": {
        "expression": {
          "Individual": {
            "Head": "['multiply', 'subtract', 'relu2']",
            "Tail": "['x0', '@2', 'x0', 'x0']",
            "Weights": "[-1.6449765582260956, -2.2079900599859705, 2.935659094403646, 3.0245387922094937, 4.560556129459673, 2.4302396035411147]",
            "Biases": "[-0.5359887412331164, -0.46058101070897717, -2.078736154242394]"
          }
        },
        "fitness": 0.9999980000252668
      }
    },
    {
      "iteration": 75,
      "generations": 15,
      "best_fitness": 0.9999980000252668,
      "perfect_found": true,
      "final_avg_fitness": 0.28985589395992906,
      "best_individual": {
        "expression": {
          "Individual": {
            "Head": "['multiply', 'not_f', '@1']",
            "Tail": "['x0', '@2', '@0', '@2']",
            "Weights": "[2.4854449880389593, -2.253119149649991, -1.6433040128124081, 0.19706191510729654, -0.7620075339986743, -0.4041259171284591]",
            "Biases": "[0.266442422008892, -1.2591922898777599, 0.782435984685488]"
          }
        },
        "fitness": 0.9999980000252668
      }
    },
    {
      "iteration": 76,
      "generations": 67,
      "best_fitness": 0.9999980000252668,
      "perfect_found": true,
      "final_avg_fitness": 0.2697273763646379,
      "best_individual": {
        "expression": {
          "Individual": {
            "Head": "['multiply', 'add', 'add']",
            "Tail": "['x0', 'x0', '@1', '@1']",
            "Weights": "[0.2722956002790396, 2.002839864556704, -6.789325549141969, -0.09458499218570182, -4.799293524990246, -7.302514548848576]",
            "Biases": "[-0.19515042979428615, 2.3432998044492788, 0.8113413636577498]"
          }
        },
        "fitness": 0.9999980000252668
      }
    },
    {
      "iteration": 77,
      "generations": 47,
      "best_fitness": 0.9999980000252668,
      "perfect_found": true,
      "final_avg_fitness": 0.28378620209182814,
      "best_individual": {
        "expression": {
          "Individual": {
            "Head": "['multiply', 'tanh', 'subtract']",
            "Tail": "['@2', 'x0', '@1', '@1']",
            "Weights": "[2.4215900877755803, 4.248715670066386, -10.06624123888487, -3.420927560396261, -0.3583541554602102, -0.7996289458187548]",
            "Biases": "[-0.17623360824788842, 0.11225396913769958, 2.2483152442379097]"
          }
        },
        "fitness": 0.9999980000252668
      }
    },
    {
      "iteration": 78,
      "generations": 20,
      "best_fitness": 0.9999980000252668,
      "perfect_found": true,
      "final_avg_fitness": 0.278204456370858,
      "best_individual": {
        "expression": {
          "Individual": {
            "Head": "['multiply', 'tanh2', '@1']",
            "Tail": "['x0', 'x0', '@0', '@2']",
            "Weights": "[1.8657599106685543, -3.685595834264422, 0.9747879690752975, -3.9169598459271064, -0.6805900394766985, -0.2769620085749245]",
            "Biases": "[0.4391876712915224, 0.7285622710479935, -3.962526123829851]"
          }
        },
        "fitness": 0.9999980000252668
      }
    },
    {
      "iteration": 79,
      "generations": 12,
      "best_fitness": 0.9999980000252668,
      "perfect_found": true,
      "final_avg_fitness": 0.26446810099145146,
      "best_individual": {
        "expression": {
          "Individual": {
            "Head": "['multiply', 'not_f', 'not_f']",
            "Tail": "['@2', 'x0', '@1', '@0']",
            "Weights": "[-4.909288054613705, 1.113637131273138, -0.7218541518343287, -1.5342248048511185, -0.04899232809439136, -0.9376264837963494]",
            "Biases": "[1.1240321735509342, -1.394598570019683, -1.4378341707129576]"
          }
        },
        "fitness": 0.9999980000252668
      }
    },
    {
      "iteration": 80,
      "generations": 99,
      "best_fitness": 0.9999980000252668,
      "perfect_found": true,
      "final_avg_fitness": 0.2804705473153912,
      "best_individual": {
        "expression": {
          "Individual": {
            "Head": "['multiply', 'not_f', '@1']",
            "Tail": "['x0', '@0', '@0', '@2']",
            "Weights": "[1.663111075456173, -2.5050106117951225, -3.584046251809776, -0.09740588733761435, 0.010529235869961628, 4.837260413829792]",
            "Biases": "[1.4518017882062315, -1.7450338411767818, 2.5965945773294132]"
          }
        },
        "fitness": 0.9999980000252668
      }
    },
    {
      "iteration": 81,
      "generations": 18,
      "best_fitness": 0.9999980000252668,
      "perfect_found": true,
      "final_avg_fitness": 0.28043940066773354,
      "best_individual": {
        "expression": {
          "Individual": {
            "Head": "['multiply', 'subtract', 'not_f']",
            "Tail": "['@2', '@1', 'x0', '@0']",
            "Weights": "[1.6408001818651643, -2.3268250416632243, 1.2167391910410967, -0.23606062178274792, 3.7328573501552587, -0.8187697204935114]",
            "Biases": "[-0.704011004611687, -0.8647920352095292, 1.7261784641550697]"
          }
        },
        "fitness": 0.9999980000252668
      }
    },
    {
      "iteration": 82,
      "generations": 16,
      "best_fitness": 0.9999980000252668,
      "perfect_found": true,
      "final_avg_fitness": 0.259558510171139,
      "best_individual": {
        "expression": {
          "Individual": {
            "Head": "['multiply', 'multiply', 'subtract']",
            "Tail": "['@1', '@0', 'x0', 'x0']",
            "Weights": "[-1.5906870063504777, 2.404250405001793, 1.8866372677812533, -0.7337936454651284, 1.94788314968971, -0.9799742582367568]",
            "Biases": "[-0.996280010421585, 1.1759820483239856, -1.6192567185097373]"
          }
        },
        "fitness": 0.9999980000252668
      }
    },
    {
      "iteration": 83,
      "generations": 28,
      "best_fitness": 0.9999980000252668,
      "perfect_found": true,
      "final_avg_fitness": 0.2777223598415492,
      "best_individual": {
        "expression": {
          "Individual": {
            "Head": "['multiply', 'not_f', '@1']",
            "Tail": "['x0', '@0', '@0', '@1']",
            "Weights": "[-1.4857734588591003, 1.1452415291583005, 5.1713514291124945, -1.40369790565397, 0.14224457246691213, -1.3453079114876734]",
            "Biases": "[0.2798635231529345, 2.8647734218318583, 0.05489080772939051]"
          }
        },
        "fitness": 0.9999980000252668
      }
    },
    {
      "iteration": 84,
      "generations": 47,
      "best_fitness": 0.9999980000252668,
      "perfect_found": true,
      "final_avg_fitness": 0.271762911143301,
      "best_individual": {
        "expression": {
          "Individual": {
            "Head": "['relu', 'multiply', 'relu2']",
            "Tail": "['@2', 'x0', 'x0', 'x0']",
            "Weights": "[-0.6456751112407354, -1.87779695274377, -3.510098333075723, 0.628187742059726, 2.337791690000246, -0.8125768274975937]",
            "Biases": "[-1.5277968771833146, 2.3848270549657373, -0.46976019569949545]"
          }
        },
        "fitness": 0.9999980000252668
      }
    },
    {
      "iteration": 85,
      "generations": 48,
      "best_fitness": 0.9999980000252668,
      "perfect_found": true,
      "final_avg_fitness": 0.2824615742754917,
      "best_individual": {
        "expression": {
          "Individual": {
            "Head": "['multiply', 'not_f', '@1']",
            "Tail": "['x0', '@2', '@2', '@1']",
            "Weights": "[3.215667115881188, -1.5830106451862862, 5.289927745575145, 0.6887752955278149, -2.371654608615684, 2.6517660959539393]",
            "Biases": "[-0.407423440394887, -0.17644592498538636, 1.435030293149594]"
          }
        },
        "fitness": 0.9999980000252668
      }
    },
    {
      "iteration": 86,
      "generations": 25,
      "best_fitness": 0.9999980000252668,
      "perfect_found": true,
      "final_avg_fitness": 0.276184035561764,
      "best_individual": {
        "expression": {
          "Individual": {
            "Head": "['multiply', 'relu', '@1']",
            "Tail": "['x0', '@1', '@1', 'x0']",
            "Weights": "[0.7349593047169056, -4.128909315654088, 2.761777243572501, -1.6988166154368733, -0.6063801655707881, -2.7562710745848547]",
            "Biases": "[0.9805872490430166, -0.9330187440155016, 0.7897931136341192]"
          }
        },
        "fitness": 0.9999980000252668
      }
    },
    {
      "iteration": 87,
      "generations": 22,
      "best_fitness": 0.9999980000252668,
      "perfect_found": true,
      "final_avg_fitness": 0.2847958287371889,
      "best_individual": {
        "expression": {
          "Individual": {
            "Head": "['multiply', 'subtract', 'relu']",
            "Tail": "['@2', '@2', 'x0', 'x0']",
            "Weights": "[3.3618917158992305, 3.265338521083154, -0.6013872810127044, 3.608663322139348, 1.8481246335714037, 1.1071097919020338]",
            "Biases": "[1.0608123671685854, -0.018193485622104266, -0.31887682337357925]"
          }
        },
        "fitness": 0.9999980000252668
      }
    },
    {
      "iteration": 88,
      "generations": 26,
      "best_fitness": 0.9999980000252668,
      "perfect_found": true,
      "final_avg_fitness": 0.26227159702416636,
      "best_individual": {
        "expression": {
          "Individual": {
            "Head": "['multiply', 'not_f', '@1']",
            "Tail": "['x0', '@2', 'x0', 'x0']",
            "Weights": "[-1.0288375180706208, 1.0135296503105495, 3.3065410150440826, 1.0656712895798914, 2.5163593923287815, 0.08873812826963498]",
            "Biases": "[-1.139366271105512, 0.9964502967431533, -1.3179678334431875]"
          }
        },
        "fitness": 0.9999980000252668
      }
    },
    {
      "iteration": 89,
      "generations": 104,
      "best_fitness": 0.9999980000252668,
      "perfect_found": true,
      "final_avg_fitness": 0.2762298667123639,
      "best_individual": {
        "expression": {
          "Individual": {
            "Head": "['not_f', 'multiply', 'not_f']",
            "Tail": "['@2', 'x0', '@0', '@1']",
            "Weights": "[2.5971861518666897, -3.0422063977508635, -5.596400046012643, -3.474071987571522, -3.969867300510782, -2.102703567043993]",
            "Biases": "[0.6197131184726712, -3.4909958808823407, -2.7035746554979063]"
          }
        },
        "fitness": 0.9999980000252668
      }
    },
    {
      "iteration": 90,
      "generations": 38,
      "best_fitness": 0.9999980000252668,
      "perfect_found": true,
      "final_avg_fitness": 0.26589333753319955,
      "best_individual": {
        "expression": {
          "Individual": {
            "Head": "['tanh', 'multiply', 'relu2']",
            "Tail": "['@2', '@0', 'x0', 'x0']",
            "Weights": "[-6.39180382634399, 3.864419315721451, 2.75567924123022, 0.5582991204873388, 1.750815395852871, 1.0862973708490677]",
            "Biases": "[0.2273556167472276, -0.21862720319764006, -1.1317311747840682]"
          }
        },
        "fitness": 0.9999980000252668
      }
    },
    {
      "iteration": 91,
      "generations": 29,
      "best_fitness": 0.9999980000252668,
      "perfect_found": true,
      "final_avg_fitness": 0.2754780391497592,
      "best_individual": {
        "expression": {
          "Individual": {
            "Head": "['multiply', 'subtract', '@1']",
            "Tail": "['x0', 'x0', 'x0', '@0']",
            "Weights": "[0.8222598105778005, -2.4420472755134233, 0.3282181732290608, -1.9691946361157933, 3.4550126331164353, 5.094038987399493]",
            "Biases": "[0.07304832059326472, -1.2360916611961912, 0.7507763174330788]"
          }
        },
        "fitness": 0.9999980000252668
      }
    },
    {
      "iteration": 92,
      "generations": 43,
      "best_fitness": 0.9999980000252668,
      "perfect_found": true,
      "final_avg_fitness": 0.2807629457176374,
      "best_individual": {
        "expression": {
          "Individual": {
            "Head": "['multiply', 'not_f', 'multiply']",
            "Tail": "['x0', '@1', '@1', '@1']",
            "Weights": "[-1.4586283861778562, -4.42802679725366, -3.9221972028902043, 1.5886830399337573, -3.8628778016559924, -0.6596755766874081]",
            "Biases": "[-0.7899356780954876, -1.304193036186426, 4.214503838738878]"
          }
        },
        "fitness": 0.9999980000252668
      }
    },
    {
      "iteration": 93,
      "generations": 30,
      "best_fitness": 0.9999980000252668,
      "perfect_found": true,
      "final_avg_fitness": 0.2763214405523689,
      "best_individual": {
        "expression": {
          "Individual": {
            "Head": "['multiply', 'not_f', '@1']",
            "Tail": "['x0', '@0', 'x0', 'x0']",
            "Weights": "[2.2794698728128884, -1.5265248770586102, 1.4166219080083111, 0.7643271773329654, 1.0681952215395003, -3.5051992080245333]",
            "Biases": "[0.45878877277189756, -0.2496624960599153, 1.1020484664648127]"
          }
        },
        "fitness": 0.9999980000252668
      }
    },
    {
      "iteration": 94,
      "generations": 27,
      "best_fitness": 0.9999980000252668,
      "perfect_found": true,
      "final_avg_fitness": 0.2618532733111362,
      "best_individual": {
        "expression": {
          "Individual": {
            "Head": "['relu', 'multiply', 'multiply']",
            "Tail": "['@2', 'x0', 'x0', '@1']",
            "Weights": "[-1.088620713543595, 3.817966080360316, 6.279672171656949, -1.8213939267245007, 1.4570203695022694, -1.764815815883192]",
            "Biases": "[-3.024937193491347, -0.883678484786308, 0.11732839571444649]"
          }
        },
        "fitness": 0.9999980000252668
      }
    },
    {
      "iteration": 95,
      "generations": 7,
      "best_fitness": 0.9999980000252668,
      "perfect_found": true,
      "final_avg_fitness": 0.26571373320667896,
      "best_individual": {
        "expression": {
          "Individual": {
            "Head": "['multiply', 'not_f', '@1']",
            "Tail": "['x0', '@1', '@0', '@0']",
            "Weights": "[2.1678803813594874, -1.3805962780518837, -1.9370473611807315, 0.8817498853878083, -0.7031396852621886, 0.7527470947695881]",
            "Biases": "[0.5227318195107279, -2.3841068881975325, -1.0602766939113708]"
          }
        },
        "fitness": 0.9999980000252668
      }
    },
    {
      "iteration": 96,
      "generations": 25,
      "best_fitness": 0.9999980000252668,
      "perfect_found": true,
      "final_avg_fitness": 0.27644886892301246,
      "best_individual": {
        "expression": {
          "Individual": {
            "Head": "['multiply', 'relu', '@1']",
            "Tail": "['x0', '@1', '@1', 'x0']",
            "Weights": "[-0.669236413383411, 3.4223693687397145, 5.068109681625106, -2.392539290102097, 2.2890736874120874, 3.229564969629759]",
            "Biases": "[-1.2656374669807609, -0.885930588537719, -0.19306042485741653]"
          }
        },
        "fitness": 0.9999980000252668
      }
    },
    {
      "iteration": 97,
      "generations": 66,
      "best_fitness": 0.9999980000252668,
      "perfect_found": true,
      "final_avg_fitness": 0.2700280920192835,
      "best_individual": {
        "expression": {
          "Individual": {
            "Head": "['multiply', 'subtract', '@1']",
            "Tail": "['x0', 'x0', 'x0', 'x0']",
            "Weights": "[-2.505937754378728, 5.060863541979247, -3.284444333875181, 2.286030730508561, -0.14557147372665535, -2.426677801393965]",
            "Biases": "[-1.2819614944873565, 0.3025617643080779, -0.10285503248881134]"
          }
        },
        "fitness": 0.9999980000252668
      }
    },
    {
      "iteration": 98,
      "generations": 27,
      "best_fitness": 0.9999980000252668,
      "perfect_found": true,
      "final_avg_fitness": 0.27881026862779773,
      "best_individual": {
        "expression": {
          "Individual": {
            "Head": "['multiply', 'multiply', 'not_f']",
            "Tail": "['@0', '@1', 'x0', '@0']",
            "Weights": "[1.4601190231962047, -4.42248040900307, -3.139146764763302, 1.5517065592045438, -0.7978195687993765, -3.6247336407436297]",
            "Biases": "[2.277009306699352, -1.2658920003410266, -1.294411328548936]"
          }
        },
        "fitness": 0.9999980000252668
      }
    },
    {
      "iteration": 99,
      "generations": 28,
      "best_fitness": 0.9999072307821895,
      "perfect_found": true,
      "final_avg_fitness": 0.2946542041777053,
      "best_individual": {
        "expression": {
          "Individual": {
            "Head": "['multiply', 'tanh2', '@1']",
            "Tail": "['x0', 'x0', 'x0', '@1']",
            "Weights": "[1.1025732329502815, -2.5093475404325627, -4.694573533484297, -3.9166997266040915, 0.49017085704754404, -1.4215587498991826]",
            "Biases": "[0.5265908909388968, 0.56939493744028, 2.737446660878805]"
          }
        },
        "fitness": 0.9999072307821895
      }
    },
    {
      "iteration": 100,
      "generations": 37,
      "best_fitness": 0.9999980000252668,
      "perfect_found": true,
      "final_avg_fitness": 0.2677174123928187,
      "best_individual": {
        "expression": {
          "Individual": {
            "Head": "['multiply', 'add', 'multiply']",
            "Tail": "['@2', '@2', 'x0', 'x0']",
            "Weights": "[-5.652206268828696, -3.0260951794671125, -4.127131299769735, 2.0159326866247156, 5.871139364480843, 2.27562133862929]",
            "Biases": "[1.4377359031969343, -0.02187403304442137, -2.9037481634432245]"
          }
        },
        "fitness": 0.9999980000252668
      }
    }
  ]
}